Workbook

Sheet Home
A1: Date | B1: Opening Balance | C1: Issue Balance | D1: Total | E1: Expense | F1: Return | O1: Commissions
A2: 44197 | B2: 0 | C2: ='1'!F18 -> 11436 | D2: ='1'!G18 -> 11436 | E2: ='1'!H18 -> 19540 | F2: ='1'!I18 -> -8104 | O2: Jazz Load | P2: =B70 -> 25946
A3: 44198 | B3: =F2 -> -8104 | C3: ='2'!F18 -> 0 | D3: ='2'!G18 -> -8104 | E3: ='2'!H18 -> 0 | F3: ='2'!I18 -> -8104 | O3: Jazz Cash | P3: =C70 -> 0
A4: 44199 | B4: =F3 -> -8104 | C4: ='3'!F18 -> 0 | D4: ='3'!G18 -> -8104 | E4: ='3'!H18 -> 0 | F4: ='3'!I18 -> -8104 | O4: Efics MFS | P4: =D70 -> 70
A5: 44200 | B5: =F4 -> -8104 | C5: ='4'!F18 -> 0 | D5: ='4'!G18 -> -8104 | E5: ='4'!H18 -> 0 | F5: ='4'!I18 -> -8104 | O5: Efics BILL | P5: =E70 -> 226
A6: 44201 | B6: =F5 -> -8104 | C6: ='5'!F18 -> 0 | D6: ='5'!G18 -> -8104 | E6: ='5'!H18 -> 0 | F6: ='5'!I18 -> -8104 | O6: SIM Commission | P6: =F70 -> 0
A7: 44202 | B7: =F6 -> -8104 | C7: ='6'!F18 -> 0 | D7: ='6'!G18 -> -8104 | E7: ='6'!H18 -> 0 | F7: ='6'!I18 -> -8104 | O7: Retail IMSI | P7: =G70 -> 0
A8: 44203 | B8: =F7 -> -8104 | C8: ='7'!F18 -> 0 | D8: ='7'!G18 -> -8104 | E8: ='7'!H18 -> 0 | F8: ='7'!I18 -> -8104 | O8: Franchise IMSI | P8: =H70 -> 0
A9: 44204 | B9: =F8 -> -8104 | C9: ='8'!F18 -> 0 | D9: ='8'!G18 -> -8104 | E9: ='8'!H18 -> 0 | F9: ='8'!I18 -> -8104 | O9: GST Comm | P9: =I70 -> 0
A10: 44205 | B10: =F9 -> -8104 | C10: ='9'!F18 -> 0 | D10: ='9'!G18 -> -8104 | E10: ='9'!H18 -> 0 | F10: ='9'!I18 -> -8104 | O10: Tax Claim Rebate | P10: =J70 -> 0
A11: 44206 | B11: =F10 -> -8104 | C11: ='10'!F18 -> 0 | D11: ='10'!G18 -> -8104 | E11: ='10'!H18 -> 0 | F11: ='10'!I18 -> -8104 | O11: MNP Comm | P11: =K70 -> 0
A12: 44207 | B12: =F11 -> -8104 | C12: ='11'!F18 -> 0 | D12: ='11'!G18 -> -8104 | E12: ='11'!H18 -> 0 | F12: ='11'!I18 -> -8104 | O12: Other | P12: =L70 -> 0
A13: 44208 | B13: =F12 -> -8104 | C13: ='12'!F18 -> 0 | D13: ='12'!G18 -> -8104 | E13: ='12'!H18 -> 0 | F13: ='12'!I18 -> -8104 | O13: Other | P13: =M70 -> 0
A14: 44209 | B14: =F13 -> -8104 | C14: ='13'!F18 -> 0 | D14: ='13'!G18 -> -8104 | E14: ='13'!H18 -> 0 | F14: ='13'!I18 -> -8104 | O14: TOTAL | P14: =SUM(P2:P13) -> 26242
A15: 44210 | B15: =F14 -> -8104 | C15: ='14'!F18 -> 0 | D15: ='14'!G18 -> -8104 | E15: ='14'!H18 -> 0 | F15: ='14'!I18 -> -8104
A16: 44211 | B16: =F15 -> -8104 | C16: ='15'!F18 -> 0 | D16: ='15'!G18 -> -8104 | E16: ='15'!H18 -> 0 | F16: ='15'!I18 -> -8104
A17: 44212 | B17: =F16 -> -8104 | C17: ='16'!F18 -> 0 | D17: ='16'!G18 -> -8104 | E17: ='16'!H18 -> 0 | F17: ='16'!I18 -> -8104
A18: 44213 | B18: =F17 -> -8104 | C18: ='17'!F18 -> 0 | D18: ='17'!G18 -> -8104 | E18: ='17'!H18 -> 0 | F18: ='17'!I18 -> -8104
A19: 44214 | B19: =F18 -> -8104 | C19: ='18'!F18 -> 0 | D19: ='18'!G18 -> -8104 | E19: ='18'!H18 -> 0 | F19: ='18'!I18 -> -8104
A20: 44215 | B20: =F19 -> -8104 | C20: ='19'!F18 -> 0 | D20: ='19'!G18 -> -8104 | E20: ='19'!H18 -> 0 | F20: ='19'!I18 -> -8104
A21: 44216 | B21: =F20 -> -8104 | C21: ='20'!F18 -> 0 | D21: ='20'!G18 -> -8104 | E21: ='20'!H18 -> 0 | F21: ='20'!I18 -> -8104
A22: 44217 | B22: =F21 -> -8104 | C22: ='21'!F18 -> 0 | D22: ='21'!G18 -> -8104 | E22: ='21'!H18 -> 0 | F22: ='21'!I18 -> -8104
A23: 44218 | B23: =F22 -> -8104 | C23: ='22'!F18 -> 0 | D23: ='22'!G18 -> -8104 | E23: ='22'!H18 -> 0 | F23: ='22'!I18 -> -8104
A24: 44219 | B24: =F23 -> -8104 | C24: ='23'!F18 -> 0 | D24: ='23'!G18 -> -8104 | E24: ='23'!H18 -> 0 | F24: ='23'!I18 -> -8104
A25: 44220 | B25: =F24 -> -8104 | C25: ='24'!F18 -> 0 | D25: ='24'!G18 -> -8104 | E25: ='24'!H18 -> 0 | F25: ='24'!I18 -> -8104
A26: 44221 | B26: =F25 -> -8104 | C26: ='25'!F18 -> 0 | D26: ='25'!G18 -> -8104 | E26: ='25'!H18 -> 0 | F26: ='25'!I18 -> -8104
A27: 44222 | B27: =F26 -> -8104 | C27: ='26'!F18 -> 0 | D27: ='26'!G18 -> -8104 | E27: ='26'!H18 -> 0 | F27: ='26'!I18 -> -8104
A28: 44223 | B28: =F27 -> -8104 | C28: ='27'!F18 -> 0 | D28: ='27'!G18 -> -8104 | E28: ='27'!H18 -> 0 | F28: ='27'!I18 -> -8104
A29: 44224 | B29: =F28 -> -8104 | C29: ='28'!F18 -> 0 | D29: ='28'!G18 -> -8104 | E29: ='28'!H18 -> 0 | F29: ='28'!I18 -> -8104
A30: 44225 | B30: =F29 -> -8104 | C30: ='29'!F18 -> 0 | D30: ='29'!G18 -> -8104 | E30: ='29'!H18 -> 0 | F30: ='29'!I18 -> -8104
A31: 44226 | B31: =F30 -> -8104 | C31: ='30'!F18 -> 0 | D31: ='30'!G18 -> -8104 | E31: ='30'!H18 -> 0 | F31: ='30'!I18 -> -8104
A32: 44227 | B32: =F31 -> -8104 | C32: ='31'!F18 -> 0 | D32: ='31'!G18 -> -8104 | E32: ='31'!H18 -> 0 | F32: ='31'!I18 -> -8104
A33: FINAL | B33: =FINAL!E18 -> -8104 | C33: =FINAL!F18 -> 14806 | D33: =FINAL!G18 -> 6702 | E33: =FINAL!H18 -> 7800 | F33: =FINAL!I18 -> -1098
A34: TOTAL | B34: 0 | C34: =SUM(C2:C33) -> 26242 | D34: 0 | E34: =SUM(E2:E33) -> 27340 | F34: 0
A37: Date | B37: Jazz Load | C37: Jazz Cash | D37: Efics MFS | E37: Efics Bill | F37: SIM Commission | G37: Retail IMSI | H37: Franchise IMSI | I37: GST Comm | J37: Tax Rebate | K37: MNP | L37: Other | M37: Other | N37: TOTAL
A38: 1 | B38: ='1'!L5 -> 11140 | C38: ='1'!M5 -> 0 | D38: ='1'!N5 -> 70 | E38: ='1'!O5 -> 226 | F38: ='1'!P5 -> 0 | G38: ='1'!Q5 -> 0 | H38: ='1'!R5 -> 0 | I38: ='1'!S5 -> 0 | ... M38: ='1'!W5 -> 0 | N38: =SUM(B38:M38) -> 11436
A39: 2 | B39: ='2'!L5 -> 0 | C39: ='2'!M5 -> 0 | D39: ='2'!N5 -> 0 | E39: ='2'!O5 -> 0 | F39: ='2'!P5 -> 0 | G39: ='2'!Q5 -> 0 | H39: ='2'!R5 -> 0 | I39: ='2'!S5 -> 0 | ... M39: ='2'!W5 -> 0 | N39: =SUM(B39:M39) -> 0
A40: 3 | B40: ='3'!L5 -> 0 | C40: ='3'!M5 -> 0 | D40: ='3'!N5 -> 0 | E40: ='3'!O5 -> 0 | F40: ='3'!P5 -> 0 | G40: ='3'!Q5 -> 0 | H40: ='3'!R5 -> 0 | I40: ='3'!S5 -> 0 | ... M40: ='3'!W5 -> 0 | N40: =SUM(B40:M40) -> 0
A41: 4 | B41: ='4'!L5 -> 0 | C41: ='4'!M5 -> 0 | D41: ='4'!N5 -> 0 | E41: ='4'!O5 -> 0 | F41: ='4'!P5 -> 0 | G41: ='4'!Q5 -> 0 | H41: ='4'!R5 -> 0 | I41: ='4'!S5 -> 0 | ... M41: ='4'!W5 -> 0 | N41: =SUM(B41:M41) -> 0
A42: 5 | B42: ='5'!L5 -> 0 | C42: ='5'!M5 -> 0 | D42: ='5'!N5 -> 0 | E42: ='5'!O5 -> 0 | F42: ='5'!P5 -> 0 | G42: ='5'!Q5 -> 0 | H42: ='5'!R5 -> 0 | I42: ='5'!S5 -> 0 | ... M42: ='5'!W5 -> 0 | N42: =SUM(B42:M42) -> 0
A43: 6 | B43: ='6'!L5 -> 0 | C43: ='6'!M5 -> 0 | D43: ='6'!N5 -> 0 | E43: ='6'!O5 -> 0 | F43: ='6'!P5 -> 0 | G43: ='6'!Q5 -> 0 | H43: ='6'!R5 -> 0 | I43: ='6'!S5 -> 0 | ... M43: ='6'!W5 -> 0 | N43: =SUM(B43:M43) -> 0
A44: 7 | B44: ='7'!L5 -> 0 | C44: ='7'!M5 -> 0 | D44: ='7'!N5 -> 0 | E44: ='7'!O5 -> 0 | F44: ='7'!P5 -> 0 | G44: ='7'!Q5 -> 0 | H44: ='7'!R5 -> 0 | I44: ='7'!S5 -> 0 | ... M44: ='7'!W5 -> 0 | N44: =SUM(B44:M44) -> 0
A45: 8 | B45: ='8'!L5 -> 0 | C45: ='8'!M5 -> 0 | D45: ='8'!N5 -> 0 | E45: ='8'!O5 -> 0 | F45: ='8'!P5 -> 0 | G45: ='8'!Q5 -> 0 | H45: ='8'!R5 -> 0 | I45: ='8'!S5 -> 0 | ... M45: ='8'!W5 -> 0 | N45: =SUM(B45:M45) -> 0
A46: 9 | B46: ='9'!L5 -> 0 | C46: ='9'!M5 -> 0 | D46: ='9'!N5 -> 0 | E46: ='9'!O5 -> 0 | F46: ='9'!P5 -> 0 | G46: ='9'!Q5 -> 0 | H46: ='9'!R5 -> 0 | I46: ='9'!S5 -> 0 | ... M46: ='9'!W5 -> 0 | N46: =SUM(B46:M46) -> 0
A47: 10 | B47: ='10'!L5 -> 0 | C47: ='10'!M5 -> 0 | D47: ='10'!N5 -> 0 | E47: ='10'!O5 -> 0 | F47: ='10'!P5 -> 0 | G47: ='10'!Q5 -> 0 | H47: ='10'!R5 -> 0 | I47: ='10'!S5 -> 0 | ... M47: ='10'!W5 -> 0 | N47: =SUM(B47:M47) -> 0
A48: 11 | B48: ='11'!L5 -> 0 | C48: ='11'!M5 -> 0 | D48: ='11'!N5 -> 0 | E48: ='11'!O5 -> 0 | F48: ='11'!P5 -> 0 | G48: ='11'!Q5 -> 0 | H48: ='11'!R5 -> 0 | I48: ='11'!S5 -> 0 | ... M48: ='11'!W5 -> 0 | N48: =SUM(B48:M48) -> 0
A49: 12 | B49: ='12'!L5 -> 0 | C49: ='12'!M5 -> 0 | D49: ='12'!N5 -> 0 | E49: ='12'!O5 -> 0 | F49: ='12'!P5 -> 0 | G49: ='12'!Q5 -> 0 | H49: ='12'!R5 -> 0 | I49: ='12'!S5 -> 0 | ... M49: ='12'!W5 -> 0 | N49: =SUM(B49:M49) -> 0
A50: 13 | B50: ='13'!L5 -> 0 | C50: ='13'!M5 -> 0 | D50: ='13'!N5 -> 0 | E50: ='13'!O5 -> 0 | F50: ='13'!P5 -> 0 | G50: ='13'!Q5 -> 0 | H50: ='13'!R5 -> 0 | I50: ='13'!S5 -> 0 | ... M50: ='13'!W5 -> 0 | N50: =SUM(B50:M50) -> 0
A51: 14 | B51: ='14'!L5 -> 0 | C51: ='14'!M5 -> 0 | D51: ='14'!N5 -> 0 | E51: ='14'!O5 -> 0 | F51: ='14'!P5 -> 0 | G51: ='14'!Q5 -> 0 | H51: ='14'!R5 -> 0 | I51: ='14'!S5 -> 0 | ... M51: ='14'!W5 -> 0 | N51: =SUM(B51:M51) -> 0
A52: 15 | B52: ='15'!L5 -> 0 | C52: ='15'!M5 -> 0 | D52: ='15'!N5 -> 0 | E52: ='15'!O5 -> 0 | F52: ='15'!P5 -> 0 | G52: ='15'!Q5 -> 0 | H52: ='15'!R5 -> 0 | I52: ='15'!S5 -> 0 | ... M52: ='15'!W5 -> 0 | N52: =SUM(B52:M52) -> 0
A53: 16 | B53: ='16'!L5 -> 0 | C53: ='16'!M5 -> 0 | D53: ='16'!N5 -> 0 | E53: ='16'!O5 -> 0 | F53: ='16'!P5 -> 0 | G53: ='16'!Q5 -> 0 | H53: ='16'!R5 -> 0 | I53: ='16'!S5 -> 0 | ... M53: ='16'!W5 -> 0 | N53: =SUM(B53:M53) -> 0
A54: 17 | B54: ='17'!L5 -> 0 | C54: ='17'!M5 -> 0 | D54: ='17'!N5 -> 0 | E54: ='17'!O5 -> 0 | F54: ='17'!P5 -> 0 | G54: ='17'!Q5 -> 0 | H54: ='17'!R5 -> 0 | I54: ='17'!S5 -> 0 | ... M54: ='17'!W5 -> 0 | N54: =SUM(B54:M54) -> 0
A55: 18 | B55: ='18'!L5 -> 0 | C55: ='18'!M5 -> 0 | D55: ='18'!N5 -> 0 | E55: ='18'!O5 -> 0 | F55: ='18'!P5 -> 0 | G55: ='18'!Q5 -> 0 | H55: ='18'!R5 -> 0 | I55: ='18'!S5 -> 0 | ... M55: ='18'!W5 -> 0 | N55: =SUM(B55:M55) -> 0
A56: 19 | B56: ='19'!L5 -> 0 | C56: ='19'!M5 -> 0 | D56: ='19'!N5 -> 0 | E56: ='19'!O5 -> 0 | F56: ='19'!P5 -> 0 | G56: ='19'!Q5 -> 0 | H56: ='19'!R5 -> 0 | I56: ='19'!S5 -> 0 | ... M56: ='19'!W5 -> 0 | N56: =SUM(B56:M56) -> 0
A57: 20 | B57: ='20'!L5 -> 0 | C57: ='20'!M5 -> 0 | D57: ='20'!N5 -> 0 | E57: ='20'!O5 -> 0 | F57: ='20'!P5 -> 0 | G57: ='20'!Q5 -> 0 | H57: ='20'!R5 -> 0 | I57: ='20'!S5 -> 0 | ... M57: ='20'!W5 -> 0 | N57: =SUM(B57:M57) -> 0
A58: 21 | B58: ='21'!L5 -> 0 | C58: ='21'!M5 -> 0 | D58: ='21'!N5 -> 0 | E58: ='21'!O5 -> 0 | F58: ='21'!P5 -> 0 | G58: ='21'!Q5 -> 0 | H58: ='21'!R5 -> 0 | I58: ='21'!S5 -> 0 | ... M58: ='21'!W5 -> 0 | N58: =SUM(B58:M58) -> 0
A59: 22 | B59: ='22'!L5 -> 0 | C59: ='22'!M5 -> 0 | D59: ='22'!N5 -> 0 | E59: ='22'!O5 -> 0 | F59: ='22'!P5 -> 0 | G59: ='22'!Q5 -> 0 | H59: ='22'!R5 -> 0 | I59: ='22'!S5 -> 0 | ... M59: ='22'!W5 -> 0 | N59: =SUM(B59:M59) -> 0
A60: 23 | B60: ='23'!L5 -> 0 | C60: ='23'!M5 -> 0 | D60: ='23'!N5 -> 0 | E60: ='23'!O5 -> 0 | F60: ='23'!P5 -> 0 | G60: ='23'!Q5 -> 0 | H60: ='23'!R5 -> 0 | I60: ='23'!S5 -> 0 | ... M60: ='23'!W5 -> 0 | N60: =SUM(B60:M60) -> 0
A61: 24 | B61: ='24'!L5 -> 0 | C61: ='24'!M5 -> 0 | D61: ='24'!N5 -> 0 | E61: ='24'!O5 -> 0 | F61: ='24'!P5 -> 0 | G61: ='24'!Q5 -> 0 | H61: ='24'!R5 -> 0 | I61: ='24'!S5 -> 0 | ... M61: ='24'!W5 -> 0 | N61: =SUM(B61:M61) -> 0
A62: 25 | B62: ='25'!L5 -> 0 | C62: ='25'!M5 -> 0 | D62: ='25'!N5 -> 0 | E62: ='25'!O5 -> 0 | F62: ='25'!P5 -> 0 | G62: ='25'!Q5 -> 0 | H62: ='25'!R5 -> 0 | I62: ='25'!S5 -> 0 | ... M62: ='25'!W5 -> 0 | N62: =SUM(B62:M62) -> 0
A63: 26 | B63: ='26'!L5 -> 0 | C63: ='26'!M5 -> 0 | D63: ='26'!N5 -> 0 | E63: ='26'!O5 -> 0 | F63: ='26'!P5 -> 0 | G63: ='26'!Q5 -> 0 | H63: ='26'!R5 -> 0 | I63: ='26'!S5 -> 0 | ... M63: ='26'!W5 -> 0 | N63: =SUM(B63:M63) -> 0
A64: 27 | B64: ='27'!L5 -> 0 | C64: ='27'!M5 -> 0 | D64: ='27'!N5 -> 0 | E64: ='27'!O5 -> 0 | F64: ='27'!P5 -> 0 | G64: ='27'!Q5 -> 0 | H64: ='27'!R5 -> 0 | I64: ='27'!S5 -> 0 | ... M64: ='27'!W5 -> 0 | N64: =SUM(B64:M64) -> 0
A65: 28 | B65: ='28'!L5 -> 0 | C65: ='28'!M5 -> 0 | D65: ='28'!N5 -> 0 | E65: ='28'!O5 -> 0 | F65: ='28'!P5 -> 0 | G65: ='28'!Q5 -> 0 | H65: ='28'!R5 -> 0 | I65: ='28'!S5 -> 0 | ... M65: ='28'!W5 -> 0 | N65: =SUM(B65:M65) -> 0
A66: 29 | B66: ='29'!L5 -> 0 | C66: ='29'!M5 -> 0 | D66: ='29'!N5 -> 0 | E66: ='29'!O5 -> 0 | F66: ='29'!P5 -> 0 | G66: ='29'!Q5 -> 0 | H66: ='29'!R5 -> 0 | I66: ='29'!S5 -> 0 | ... M66: ='29'!W5 -> 0 | N66: =SUM(B66:M66) -> 0
A67: 30 | B67: ='30'!L5 -> 0 | C67: ='30'!M5 -> 0 | D67: ='30'!N5 -> 0 | E67: ='30'!O5 -> 0 | F67: ='30'!P5 -> 0 | G67: ='30'!Q5 -> 0 | H67: ='30'!R5 -> 0 | I67: ='30'!S5 -> 0 | ... M67: ='30'!W5 -> 0 | N67: =SUM(B67:M67) -> 0
A68: 31 | B68: ='31'!L5 -> 0 | C68: ='31'!M5 -> 0 | D68: ='31'!N5 -> 0 | E68: ='31'!O5 -> 0 | F68: ='31'!P5 -> 0 | G68: ='31'!Q5 -> 0 | H68: ='31'!R5 -> 0 | I68: ='31'!S5 -> 0 | ... M68: ='31'!W5 -> 0 | N68: =SUM(B68:M68) -> 0
A69: FINAL | B69: =FINAL!F3 -> 14806 | C69: =FINAL!F4 -> 0 | D69: =FINAL!F5 -> 0 | E69: =FINAL!F6 -> 0 | F69: =FINAL!F7 -> 0 | G69: =FINAL!F8 -> 0 | H69: =FINAL!F9 -> 0 | I69: =FINAL!F10 -> 0 | J69: =FINAL!F11 -> 0 | K69: =FINAL!F11 -> 0 | L69: =FINAL!F13 -> 0 | M69: =FINAL!F14 -> 0 | N69: =SUM(B69:M69) -> 14806
A70: Total | B70: =SUM(B38:B69) -> 25946 | C70: =SUM(C38:C69) -> 0 | D70: =SUM(D38:D69) -> 70 | E70: =SUM(E38:E69) -> 226 | F70: =SUM(F38:F69) -> 0 | G70: =SUM(G38:G69) -> 0 | H70: =SUM(H38:H69) -> 0 | I70: =SUM(I38:I69) -> 0 | ... N70: =SUM(N38:N69) -> 26242

Sheet 1
A1: EXPENSES
A2: Name | B2: Description | C2: Amount | E2: Commissions | H2: Franchise Owner
A3: Akhtar | B3: Salary March-2026 | C3: 18000 | E3: Jazz Load | F3: 11140 | H3: Opening Bal | I3: 91856
A4: Akhtar | B4: CHAY+BIST+WATER ( FAWAD SB | C4: 790 | E4: Jazz Cash | H4: AKHTAR | I4: 200 | K4: Date | L4: Jazz Load | M4: Jazz Cash | N4: Efics MFS | O4: Efics Bill | P4: SIM Commission | Q4: Retail IMSI | R4: Franchise IMSI | S4: GST Comm | T4: Tax Rebate | U4: MNP | V4: Other | W4: Other | X4: TOTAL
A5: Akhtar | B5: COFFEE ( FAWAD SB | C5: 750 | E5: Efics MFS | F5: 70 | H5: CASH | I5: 10000 | K5: 1 | L5: =F3 -> 11140 | M5: =F4 -> 0 | N5: =F5 -> 70 | O5: =F6 -> 226 | P5: =F7 -> 0 | Q5: =F8 -> 0 | R5: =F9 -> 0 | S5: =F10 -> 0 | T5: =F11 -> 0 | U5: =F12 -> 0 | V5: =F13 -> 0 | W5: =F14 -> 0 | X5: =SUM(L5:W5) -> 11436
E6: Efics BILL | F6: 226
E7: SIM Commission
E8: Retail IMSI
E9: Franchise IMSI
E10: GST Comm
E11: Tax Claim Rebate
E12: MNP Comm
E13: Other
E14: Other
E15: Total | F15: =SUM(F3:F14) -> 11436 | H15: Total | I15: =SUM(I3:I14) -> 102056
E17: Opening Bal | F17: Issue Balance | G17: Total | H17: Expense | I17: Return
E18: 0 | F18: =F15 -> 11436 | G18: =F18+E18 -> 11436 | H18: =C30 -> 19540 | I18: =G18-H18 -> -8104
E20: Credit
E21: Name | F21: Opening | G21: Today | H21: Receive | I21: Balance
E22: ALI OLAKH | F22: 20126 | I22: =F22+G22-H22 -> 20126
E23: Usman cheema | G23: 410 | I23: =F23+G23-H23 -> 410
E24: AKHTAR | F24: 5000 | H24: 5000 | I24: =F24+G24-H24 -> 0
E25: IMRAN OLAKH | F25: 8300 | I25: =F25+G25-H25 -> 8300
E26: irfan DO | F26: 10000 | I26: =F26+G26-H26 -> 10000
E27: Naveed DO | F27: 20000 | I27: =F27+G27-H27 -> 20000
E28: Qurat ul Anny | F28: 1000 | I28: =F28+G28-H28 -> 1000
E29: SARAM CCR | F29: 1000 | I29: =F29+G29-H29 -> 1000
A30: TOTAL | C30: =SUM(C3:C29) -> 19540 | E30: TATAS CCR | F30: 5000 | I30: =F30+G30-H30 -> 5000
I31: =F31+G31-H31 -> 0
I32: =F32+G32-H32 -> 0
I33: =F33+G33-H33 -> 0
I34: =F34+G34-H34 -> 0
I35: =F35+G35-H35 -> 0
I36: =F36+G36-H36 -> 0
I37: =F37+G37-H37 -> 0
I38: =F38+G38-H38 -> 0
I39: =F39+G39-H39 -> 0
I40: =F40+G40-H40 -> 0
E41: Total | F41: =SUM(F22:F40) -> 70426 | G41: =SUM(G22:G40) -> 410 | H41: =SUM(H22:H40) -> 5000 | I41: =F41+G41-H41 -> 65836

Sheet 2
A1: EXPENSES
A2: Name | B2: Description | C2: Amount | E2: Commissions | H2: Franchise Owner
E3: Jazz Load | H3: Opening Bal | I3: ='1'!I15 -> 102056
E4: Jazz Cash | K4: Date | L4: Jazz Load | M4: Jazz Cash | N4: Efics MFS | O4: Efics Bill | P4: SIM Commission | Q4: Retail IMSI | R4: Franchise IMSI | S4: GST Comm | T4: Tax Rebate | U4: MNP | V4: Other | W4: Other | X4: TOTAL
E5: Efics MFS | K5: 2 | L5: =F3 -> 0 | M5: =F4 -> 0 | N5: =F5 -> 0 | O5: =F6 -> 0 | P5: =F7 -> 0 | Q5: =F8 -> 0 | R5: =F9 -> 0 | S5: =F10 -> 0 | T5: =F11 -> 0 | U5: =F12 -> 0 | V5: =F13 -> 0 | W5: =F14 -> 0 | X5: =SUM(L5:W5) -> 0
E6: Efics BILL
E7: SIM Commission
E8: Retail IMSI
E9: Franchise IMSI
E10: GST Comm
E11: Tax Claim Rebate
E12: MNP Comm
E13: Other
E14: Other
E15: Total | F15: =SUM(F3:F14) -> 0 | H15: Total | I15: =SUM(I3:I14) -> 102056
E17: Opening Bal | F17: Issue Balance | G17: Total | H17: Expense | I17: Return
E18: ='1'!I18 -> -8104 | F18: =F15 -> 0 | G18: =F18+E18 -> -8104 | H18: =C30 -> 0 | I18: =G18-H18 -> -8104
E20: Credit
E21: Name | F21: Opening | G21: Today | H21: Receive | I21: Balance
F22: ='1'!I22 -> 20126 | I22: =F22+G22-H22 -> 20126
F23: ='1'!I23 -> 410 | I23: =F23+G23-H23 -> 410
F24: ='1'!I24 -> 0 | I24: =F24+G24-H24 -> 0
F25: ='1'!I25 -> 8300 | I25: =F25+G25-H25 -> 8300
F26: ='1'!I26 -> 10000 | I26: =F26+G26-H26 -> 10000
F27: ='1'!I27 -> 20000 | I27: =F27+G27-H27 -> 20000
F28: ='1'!I28 -> 1000 | I28: =F28+G28-H28 -> 1000
F29: ='1'!I29 -> 1000 | I29: =F29+G29-H29 -> 1000
A30: TOTAL | C30: =SUM(C3:C29) -> 0 | F30: ='1'!I30 -> 5000 | I30: =F30+G30-H30 -> 5000
F31: ='1'!I31 -> 0 | I31: =F31+G31-H31 -> 0
F32: ='1'!I32 -> 0 | I32: =F32+G32-H32 -> 0
F33: ='1'!I33 -> 0 | I33: =F33+G33-H33 -> 0
F34: ='1'!I34 -> 0 | I34: =F34+G34-H34 -> 0
F35: ='1'!I35 -> 0 | I35: =F35+G35-H35 -> 0
F36: ='1'!I36 -> 0 | I36: =F36+G36-H36 -> 0
F37: ='1'!I37 -> 0 | I37: =F37+G37-H37 -> 0
F38: ='1'!I38 -> 0 | I38: =F38+G38-H38 -> 0
F39: ='1'!I39 -> 0 | I39: =F39+G39-H39 -> 0
F40: ='1'!I40 -> 0 | I40: =F40+G40-H40 -> 0
E41: Total | F41: =SUM(F22:F40) -> 65836 | G41: =SUM(G22:G40) -> 0 | H41: =SUM(H22:H40) -> 0 | I41: =F41+G41-H41 -> 65836

Sheet 3
A1: EXPENSES
A2: Name | B2: Description | C2: Amount | E2: Commissions | H2: Franchise Owner
E3: Jazz Load | H3: Opening Bal | I3: ='2'!I15 -> 102056
E4: Jazz Cash | K4: Date | L4: Jazz Load | M4: Jazz Cash | N4: Efics MFS | O4: Efics Bill | P4: SIM Commission | Q4: Retail IMSI | R4: Franchise IMSI | S4: GST Comm | T4: Tax Rebate | U4: MNP | V4: Other | W4: Other | X4: TOTAL
E5: Efics MFS | K5: 3 | L5: =F3 -> 0 | M5: =F4 -> 0 | N5: =F5 -> 0 | O5: =F6 -> 0 | P5: =F7 -> 0 | Q5: =F8 -> 0 | R5: =F9 -> 0 | S5: =F10 -> 0 | T5: =F11 -> 0 | U5: =F12 -> 0 | V5: =F13 -> 0 | W5: =F14 -> 0 | X5: =SUM(L5:W5) -> 0
E6: Efics BILL
E7: SIM Commission
E8: Retail IMSI
E9: Franchise IMSI
E10: GST Comm
E11: Tax Claim Rebate
E12: MNP Comm
E13: Other
E14: Other
E15: Total | F15: =SUM(F3:F14) -> 0 | H15: Total | I15: =SUM(I3:I14) -> 102056
E17: Opening Bal | F17: Issue Balance | G17: Total | H17: Expense | I17: Return
E18: ='2'!I18 -> -8104 | F18: =F15 -> 0 | G18: =F18+E18 -> -8104 | H18: =C30 -> 0 | I18: =G18-H18 -> -8104
E20: Credit
E21: Name | F21: Opening | G21: Today | H21: Receive | I21: Balance
F22: ='2'!I22 -> 20126 | I22: =F22+G22-H22 -> 20126
F23: ='2'!I23 -> 410 | I23: =F23+G23-H23 -> 410
F24: ='2'!I24 -> 0 | I24: =F24+G24-H24 -> 0
F25: ='2'!I25 -> 8300 | I25: =F25+G25-H25 -> 8300
F26: ='2'!I26 -> 10000 | I26: =F26+G26-H26 -> 10000
F27: ='2'!I27 -> 20000 | I27: =F27+G27-H27 -> 20000
F28: ='2'!I28 -> 1000 | I28: =F28+G28-H28 -> 1000
F29: ='2'!I29 -> 1000 | I29: =F29+G29-H29 -> 1000
A30: TOTAL | C30: =SUM(C3:C29) -> 0 | F30: ='2'!I30 -> 5000 | I30: =F30+G30-H30 -> 5000
F31: ='2'!I31 -> 0 | I31: =F31+G31-H31 -> 0
F32: ='2'!I32 -> 0 | I32: =F32+G32-H32 -> 0
F33: ='2'!I33 -> 0 | I33: =F33+G33-H33 -> 0
F34: ='2'!I34 -> 0 | I34: =F34+G34-H34 -> 0
F35: ='2'!I35 -> 0 | I35: =F35+G35-H35 -> 0
F36: ='2'!I36 -> 0 | I36: =F36+G36-H36 -> 0
F37: ='2'!I37 -> 0 | I37: =F37+G37-H37 -> 0
F38: ='2'!I38 -> 0 | I38: =F38+G38-H38 -> 0
F39: ='2'!I39 -> 0 | I39: =F39+G39-H39 -> 0
F40: ='2'!I40 -> 0 | I40: =F40+G40-H40 -> 0
E41: Total | F41: =SUM(F22:F40) -> 65836 | G41: =SUM(G22:G40) -> 0 | H41: =SUM(H22:H40) -> 0 | I41: =F41+G41-H41 -> 65836

Sheet 4
A1: EXPENSES
A2: Name | B2: Description | C2: Amount | E2: Commissions | H2: Franchise Owner
E3: Jazz Load | H3: Opening Bal | I3: ='3'!I15 -> 102056
E4: Jazz Cash | K4: Date | L4: Jazz Load | M4: Jazz Cash | N4: Efics MFS | O4: Efics Bill | P4: SIM Commission | Q4: Retail IMSI | R4: Franchise IMSI | S4: GST Comm | T4: Tax Rebate | U4: MNP | V4: Other | W4: Other | X4: TOTAL
E5: Efics MFS | K5: 4 | L5: =F3 -> 0 | M5: =F4 -> 0 | N5: =F5 -> 0 | O5: =F6 -> 0 | P5: =F7 -> 0 | Q5: =F8 -> 0 | R5: =F9 -> 0 | S5: =F10 -> 0 | T5: =F11 -> 0 | U5: =F12 -> 0 | V5: =F13 -> 0 | W5: =F14 -> 0 | X5: =SUM(L5:W5) -> 0
E6: Efics BILL
E7: SIM Commission
E8: Retail IMSI
E9: Franchise IMSI
E10: GST Comm
E11: Tax Claim Rebate
E12: MNP Comm
E13: Other
E14: Other
E15: Total | F15: =SUM(F3:F14) -> 0 | H15: Total | I15: =SUM(I3:I14) -> 102056
E17: Opening Bal | F17: Issue Balance | G17: Total | H17: Expense | I17: Return
E18: ='3'!I18 -> -8104 | F18: =F15 -> 0 | G18: =F18+E18 -> -8104 | H18: =C30 -> 0 | I18: =G18-H18 -> -8104
E20: Credit
E21: Name | F21: Opening | G21: Today | H21: Receive | I21: Balance
F22: ='3'!I22 -> 20126 | I22: =F22+G22-H22 -> 20126
F23: ='3'!I23 -> 410 | I23: =F23+G23-H23 -> 410
F24: ='3'!I24 -> 0 | I24: =F24+G24-H24 -> 0
F25: ='3'!I25 -> 8300 | I25: =F25+G25-H25 -> 8300
F26: ='3'!I26 -> 10000 | I26: =F26+G26-H26 -> 10000
F27: ='3'!I27 -> 20000 | I27: =F27+G27-H27 -> 20000
F28: ='3'!I28 -> 1000 | I28: =F28+G28-H28 -> 1000
F29: ='3'!I29 -> 1000 | I29: =F29+G29-H29 -> 1000
A30: TOTAL | C30: =SUM(C3:C29) -> 0 | F30: ='3'!I30 -> 5000 | I30: =F30+G30-H30 -> 5000
F31: ='3'!I31 -> 0 | I31: =F31+G31-H31 -> 0
F32: ='3'!I32 -> 0 | I32: =F32+G32-H32 -> 0
F33: ='3'!I33 -> 0 | I33: =F33+G33-H33 -> 0
F34: ='3'!I34 -> 0 | I34: =F34+G34-H34 -> 0
F35: ='3'!I35 -> 0 | I35: =F35+G35-H35 -> 0
F36: ='3'!I36 -> 0 | I36: =F36+G36-H36 -> 0
F37: ='3'!I37 -> 0 | I37: =F37+G37-H37 -> 0
F38: ='3'!I38 -> 0 | I38: =F38+G38-H38 -> 0
F39: ='3'!I39 -> 0 | I39: =F39+G39-H39 -> 0
F40: ='3'!I40 -> 0 | I40: =F40+G40-H40 -> 0
E41: Total | F41: =SUM(F22:F40) -> 65836 | G41: =SUM(G22:G40) -> 0 | H41: =SUM(H22:H40) -> 0 | I41: =F41+G41-H41 -> 65836

Sheet 5
A1: EXPENSES
A2: Name | B2: Description | C2: Amount | E2: Commissions | H2: Franchise Owner
E3: Jazz Load | H3: Opening Bal | I3: ='4'!I15 -> 102056
E4: Jazz Cash | K4: Date | L4: Jazz Load | M4: Jazz Cash | N4: Efics MFS | O4: Efics Bill | P4: SIM Commission | Q4: Retail IMSI | R4: Franchise IMSI | S4: GST Comm | T4: Tax Rebate | U4: MNP | V4: Other | W4: Other | X4: TOTAL
E5: Efics MFS | K5: 5 | L5: =F3 -> 0 | M5: =F4 -> 0 | N5: =F5 -> 0 | O5: =F6 -> 0 | P5: =F7 -> 0 | Q5: =F8 -> 0 | R5: =F9 -> 0 | S5: =F10 -> 0 | T5: =F11 -> 0 | U5: =F12 -> 0 | V5: =F13 -> 0 | W5: =F14 -> 0 | X5: =SUM(L5:W5) -> 0
E6: Efics BILL
E7: SIM Commission
A8: AKHTAR | E8: Retail IMSI
A9: ABID | E9: Franchise IMSI
A10: TETAS | E10: GST Comm
A11: SEHAR | E11: Tax Claim Rebate
A12: SARAM | E12: MNP Comm
A13: Qurat ul Anny | E13: Other
E14: Other
E15: Total | F15: =SUM(F3:F14) -> 0 | H15: Total | I15: =SUM(I3:I14) -> 102056
E17: Opening Bal | F17: Issue Balance | G17: Total | H17: Expense | I17: Return
E18: ='4'!I18 -> -8104 | F18: =F15 -> 0 | G18: =F18+E18 -> -8104 | H18: =C30 -> 0 | I18: =G18-H18 -> -8104
E20: Credit
E21: Name | F21: Opening | G21: Today | H21: Receive | I21: Balance
F22: ='4'!I22 -> 20126 | I22: =F22+G22-H22 -> 20126
F23: ='4'!I23 -> 410 | I23: =F23+G23-H23 -> 410
F24: ='4'!I24 -> 0 | I24: =F24+G24-H24 -> 0
F25: ='4'!I25 -> 8300 | I25: =F25+G25-H25 -> 8300
F26: ='4'!I26 -> 10000 | I26: =F26+G26-H26 -> 10000
F27: ='4'!I27 -> 20000 | I27: =F27+G27-H27 -> 20000
F28: ='4'!I28 -> 1000 | I28: =F28+G28-H28 -> 1000
F29: ='4'!I29 -> 1000 | I29: =F29+G29-H29 -> 1000
A30: TOTAL | C30: =SUM(C3:C29) -> 0 | F30: ='4'!I30 -> 5000 | I30: =F30+G30-H30 -> 5000
F31: ='4'!I31 -> 0 | I31: =F31+G31-H31 -> 0
F32: ='4'!I32 -> 0 | I32: =F32+G32-H32 -> 0
F33: ='4'!I33 -> 0 | I33: =F33+G33-H33 -> 0
F34: ='4'!I34 -> 0 | I34: =F34+G34-H34 -> 0
F35: ='4'!I35 -> 0 | I35: =F35+G35-H35 -> 0
F36: ='4'!I36 -> 0 | I36: =F36+G36-H36 -> 0
F37: ='4'!I37 -> 0 | I37: =F37+G37-H37 -> 0
F38: ='4'!I38 -> 0 | I38: =F38+G38-H38 -> 0
F39: ='4'!I39 -> 0 | I39: =F39+G39-H39 -> 0
F40: ='4'!I40 -> 0 | I40: =F40+G40-H40 -> 0
E41: Total | F41: =SUM(F22:F40) -> 65836 | G41: =SUM(G22:G40) -> 0 | H41: =SUM(H22:H40) -> 0 | I41: =F41+G41-H41 -> 65836

Sheet 6
A1: EXPENSES
A2: Name | B2: Description | C2: Amount | E2: Commissions | H2: Franchise Owner
E3: Jazz Load | H3: Opening Bal | I3: ='5'!I15 -> 102056
E4: Jazz Cash | K4: Date | L4: Jazz Load | M4: Jazz Cash | N4: Efics MFS | O4: Efics Bill | P4: SIM Commission | Q4: Retail IMSI | R4: Franchise IMSI | S4: GST Comm | T4: Tax Rebate | U4: MNP | V4: Other | W4: Other | X4: TOTAL
E5: Efics MFS | K5: 6 | L5: =F3 -> 0 | M5: =F4 -> 0 | N5: =F5 -> 0 | O5: =F6 -> 0 | P5: =F7 -> 0 | Q5: =F8 -> 0 | R5: =F9 -> 0 | S5: =F10 -> 0 | T5: =F11 -> 0 | U5: =F12 -> 0 | V5: =F13 -> 0 | W5: =F14 -> 0 | X5: =SUM(L5:W5) -> 0
E6: Efics BILL
E7: SIM Commission
E8: Retail IMSI
E9: Franchise IMSI
E10: GST Comm
E11: Tax Claim Rebate
E12: MNP Comm
E13: Other
E14: Other
E15: Total | F15: =SUM(F3:F14) -> 0 | H15: Total | I15: =SUM(I3:I14) -> 102056
E17: Opening Bal | F17: Issue Balance | G17: Total | H17: Expense | I17: Return
E18: ='5'!I18 -> -8104 | F18: =F15 -> 0 | G18: =F18+E18 -> -8104 | H18: =C30 -> 0 | I18: =G18-H18 -> -8104
E20: Credit
E21: Name | F21: Opening | G21: Today | H21: Receive | I21: Balance
F22: ='5'!I22 -> 20126 | I22: =F22+G22-H22 -> 20126
F23: ='5'!I23 -> 410 | I23: =F23+G23-H23 -> 410
F24: ='5'!I24 -> 0 | I24: =F24+G24-H24 -> 0
F25: ='5'!I25 -> 8300 | I25: =F25+G25-H25 -> 8300
F26: ='5'!I26 -> 10000 | I26: =F26+G26-H26 -> 10000
F27: ='5'!I27 -> 20000 | I27: =F27+G27-H27 -> 20000
F28: ='5'!I28 -> 1000 | I28: =F28+G28-H28 -> 1000
F29: ='5'!I29 -> 1000 | I29: =F29+G29-H29 -> 1000
A30: TOTAL | C30: =SUM(C3:C29) -> 0 | F30: ='5'!I30 -> 5000 | I30: =F30+G30-H30 -> 5000
F31: ='5'!I31 -> 0 | I31: =F31+G31-H31 -> 0
F32: ='5'!I32 -> 0 | I32: =F32+G32-H32 -> 0
F33: ='5'!I33 -> 0 | I33: =F33+G33-H33 -> 0
F34: ='5'!I34 -> 0 | I34: =F34+G34-H34 -> 0
F35: ='5'!I35 -> 0 | I35: =F35+G35-H35 -> 0
F36: ='5'!I36 -> 0 | I36: =F36+G36-H36 -> 0
F37: ='5'!I37 -> 0 | I37: =F37+G37-H37 -> 0
F38: ='5'!I38 -> 0 | I38: =F38+G38-H38 -> 0
F39: ='5'!I39 -> 0 | I39: =F39+G39-H39 -> 0
F40: ='5'!I40 -> 0 | I40: =F40+G40-H40 -> 0
E41: Total | F41: =SUM(F22:F40) -> 65836 | G41: =SUM(G22:G40) -> 0 | H41: =SUM(H22:H40) -> 0 | I41: =F41+G41-H41 -> 65836

Sheet 7
A1: EXPENSES
A2: Name | B2: Description | C2: Amount | E2: Commissions | H2: Franchise Owner
A3: AKHTAR | E3: Jazz Load | H3: Opening Bal | I3: ='6'!I15 -> 102056
E4: Jazz Cash | K4: Date | L4: Jazz Load | M4: Jazz Cash | N4: Efics MFS | O4: Efics Bill | P4: SIM Commission | Q4: Retail IMSI | R4: Franchise IMSI | S4: GST Comm | T4: Tax Rebate | U4: MNP | V4: Other | W4: Other | X4: TOTAL
E5: Efics MFS | K5: 7 | L5: =F3 -> 0 | M5: =F4 -> 0 | N5: =F5 -> 0 | O5: =F6 -> 0 | P5: =F7 -> 0 | Q5: =F8 -> 0 | R5: =F9 -> 0 | S5: =F10 -> 0 | T5: =F11 -> 0 | U5: =F12 -> 0 | V5: =F13 -> 0 | W5: =F14 -> 0 | X5: =SUM(L5:W5) -> 0
E6: Efics BILL
E7: SIM Commission
E8: Retail IMSI
E9: Franchise IMSI
E10: GST Comm
E11: Tax Claim Rebate
E12: MNP Comm
E13: Other
E14: Other
E15: Total | F15: =SUM(F3:F14) -> 0 | H15: Total | I15: =SUM(I3:I14) -> 102056
E17: Opening Bal | F17: Issue Balance | G17: Total | H17: Expense | I17: Return
E18: ='6'!I18 -> -8104 | F18: =F15 -> 0 | G18: =F18+E18 -> -8104 | H18: =C30 -> 0 | I18: =G18-H18 -> -8104
E20: Credit
E21: Name | F21: Opening | G21: Today | H21: Receive | I21: Balance
F22: ='6'!I22 -> 20126 | I22: =F22+G22-H22 -> 20126
F23: ='6'!I23 -> 410 | I23: =F23+G23-H23 -> 410
F24: ='6'!I24 -> 0 | I24: =F24+G24-H24 -> 0
F25: ='6'!I25 -> 8300 | I25: =F25+G25-H25 -> 8300
F26: ='6'!I26 -> 10000 | I26: =F26+G26-H26 -> 10000
F27: ='6'!I27 -> 20000 | I27: =F27+G27-H27 -> 20000
F28: ='6'!I28 -> 1000 | I28: =F28+G28-H28 -> 1000
F29: ='6'!I29 -> 1000 | I29: =F29+G29-H29 -> 1000
A30: TOTAL | C30: =SUM(C3:C29) -> 0 | F30: ='6'!I30 -> 5000 | I30: =F30+G30-H30 -> 5000
F31: ='6'!I31 -> 0 | I31: =F31+G31-H31 -> 0
F32: ='6'!I32 -> 0 | I32: =F32+G32-H32 -> 0
F33: ='6'!I33 -> 0 | I33: =F33+G33-H33 -> 0
F34: ='6'!I34 -> 0 | I34: =F34+G34-H34 -> 0
F35: ='6'!I35 -> 0 | I35: =F35+G35-H35 -> 0
F36: ='6'!I36 -> 0 | I36: =F36+G36-H36 -> 0
F37: ='6'!I37 -> 0 | I37: =F37+G37-H37 -> 0
F38: ='6'!I38 -> 0 | I38: =F38+G38-H38 -> 0
F39: ='6'!I39 -> 0 | I39: =F39+G39-H39 -> 0
F40: ='6'!I40 -> 0 | I40: =F40+G40-H40 -> 0
E41: Total | F41: =SUM(F22:F40) -> 65836 | G41: =SUM(G22:G40) -> 0 | H41: =SUM(H22:H40) -> 0 | I41: =F41+G41-H41 -> 65836

Sheet 8
A1: EXPENSES
A2: Name | B2: Description | C2: Amount | E2: Commissions | H2: Franchise Owner
E3: Jazz Load | H3: Opening Bal | I3: ='7'!I15 -> 102056
E4: Jazz Cash | K4: Date | L4: Jazz Load | M4: Jazz Cash | N4: Efics MFS | O4: Efics Bill | P4: SIM Commission | Q4: Retail IMSI | R4: Franchise IMSI | S4: GST Comm | T4: Tax Rebate | U4: MNP | V4: Other | W4: Other | X4: TOTAL
E5: Efics MFS | K5: 8 | L5: =F3 -> 0 | M5: =F4 -> 0 | N5: =F5 -> 0 | O5: =F6 -> 0 | P5: =F7 -> 0 | Q5: =F8 -> 0 | R5: =F9 -> 0 | S5: =F10 -> 0 | T5: =F11 -> 0 | U5: =F12 -> 0 | V5: =F13 -> 0 | W5: =F14 -> 0 | X5: =SUM(L5:W5) -> 0
E6: Efics BILL
E7: SIM Commission
E8: Retail IMSI
E9: Franchise IMSI
E10: GST Comm
E11: Tax Claim Rebate
E12: MNP Comm
E13: Other
E14: Other
E15: Total | F15: =SUM(F3:F14) -> 0 | H15: Total | I15: =SUM(I3:I14) -> 102056
E17: Opening Bal | F17: Issue Balance | G17: Total | H17: Expense | I17: Return
E18: ='7'!I18 -> -8104 | F18: =F15 -> 0 | G18: =F18+E18 -> -8104 | H18: =C30 -> 0 | I18: =G18-H18 -> -8104
E20: Credit
E21: Name | F21: Opening | G21: Today | H21: Receive | I21: Balance
F22: ='7'!I22 -> 20126 | I22: =F22+G22-H22 -> 20126
F23: ='7'!I23 -> 410 | I23: =F23+G23-H23 -> 410
F24: ='7'!I24 -> 0 | I24: =F24+G24-H24 -> 0
F25: ='7'!I25 -> 8300 | I25: =F25+G25-H25 -> 8300
F26: ='7'!I26 -> 10000 | I26: =F26+G26-H26 -> 10000
F27: ='7'!I27 -> 20000 | I27: =F27+G27-H27 -> 20000
F28: ='7'!I28 -> 1000 | I28: =F28+G28-H28 -> 1000
F29: ='7'!I29 -> 1000 | I29: =F29+G29-H29 -> 1000
A30: TOTAL | C30: =SUM(C3:C29) -> 0 | F30: ='7'!I30 -> 5000 | I30: =F30+G30-H30 -> 5000
F31: ='7'!I31 -> 0 | I31: =F31+G31-H31 -> 0
F32: ='7'!I32 -> 0 | I32: =F32+G32-H32 -> 0
F33: ='7'!I33 -> 0 | I33: =F33+G33-H33 -> 0
F34: ='7'!I34 -> 0 | I34: =F34+G34-H34 -> 0
F35: ='7'!I35 -> 0 | I35: =F35+G35-H35 -> 0
F36: ='7'!I36 -> 0 | I36: =F36+G36-H36 -> 0
F37: ='7'!I37 -> 0 | I37: =F37+G37-H37 -> 0
F38: ='7'!I38 -> 0 | I38: =F38+G38-H38 -> 0
F39: ='7'!I39 -> 0 | I39: =F39+G39-H39 -> 0
F40: ='7'!I40 -> 0 | I40: =F40+G40-H40 -> 0
E41: Total | F41: =SUM(F22:F40) -> 65836 | G41: =SUM(G22:G40) -> 0 | H41: =SUM(H22:H40) -> 0 | I41: =F41+G41-H41 -> 65836

Sheet 9
A1: EXPENSES
A2: Name | B2: Description | C2: Amount | E2: Commissions | H2: Franchise Owner
E3: Jazz Load | H3: Opening Bal | I3: ='8'!I15 -> 102056
E4: Jazz Cash | K4: Date | L4: Jazz Load | M4: Jazz Cash | N4: Efics MFS | O4: Efics Bill | P4: SIM Commission | Q4: Retail IMSI | R4: Franchise IMSI | S4: GST Comm | T4: Tax Rebate | U4: MNP | V4: Other | W4: Other | X4: TOTAL
E5: Efics MFS | K5: 9 | L5: =F3 -> 0 | M5: =F4 -> 0 | N5: =F5 -> 0 | O5: =F6 -> 0 | P5: =F7 -> 0 | Q5: =F8 -> 0 | R5: =F9 -> 0 | S5: =F10 -> 0 | T5: =F11 -> 0 | U5: =F12 -> 0 | V5: =F13 -> 0 | W5: =F14 -> 0 | X5: =SUM(L5:W5) -> 0
E6: Efics BILL
E7: SIM Commission
E8: Retail IMSI
E9: Franchise IMSI
E10: GST Comm
E11: Tax Claim Rebate
E12: MNP Comm
E13: Other
E14: Other
E15: Total | F15: =SUM(F3:F14) -> 0 | H15: Total | I15: =SUM(I3:I14) -> 102056
E17: Opening Bal | F17: Issue Balance | G17: Total | H17: Expense | I17: Return
E18: ='8'!I18 -> -8104 | F18: =F15 -> 0 | G18: =F18+E18 -> -8104 | H18: =C30 -> 0 | I18: =G18-H18 -> -8104
E20: Credit
E21: Name | F21: Opening | G21: Today | H21: Receive | I21: Balance
F22: ='8'!I22 -> 20126 | I22: =F22+G22-H22 -> 20126
F23: ='8'!I23 -> 410 | I23: =F23+G23-H23 -> 410
F24: ='8'!I24 -> 0 | I24: =F24+G24-H24 -> 0
F25: ='8'!I25 -> 8300 | I25: =F25+G25-H25 -> 8300
F26: ='8'!I26 -> 10000 | I26: =F26+G26-H26 -> 10000
F27: ='8'!I27 -> 20000 | I27: =F27+G27-H27 -> 20000
F28: ='8'!I28 -> 1000 | I28: =F28+G28-H28 -> 1000
F29: ='8'!I29 -> 1000 | I29: =F29+G29-H29 -> 1000
A30: TOTAL | C30: =SUM(C3:C29) -> 0 | F30: ='8'!I30 -> 5000 | I30: =F30+G30-H30 -> 5000
F31: ='8'!I31 -> 0 | I31: =F31+G31-H31 -> 0
F32: ='8'!I32 -> 0 | I32: =F32+G32-H32 -> 0
F33: ='8'!I33 -> 0 | I33: =F33+G33-H33 -> 0
F34: ='8'!I34 -> 0 | I34: =F34+G34-H34 -> 0
F35: ='8'!I35 -> 0 | I35: =F35+G35-H35 -> 0
F36: ='8'!I36 -> 0 | I36: =F36+G36-H36 -> 0
F37: ='8'!I37 -> 0 | I37: =F37+G37-H37 -> 0
F38: ='8'!I38 -> 0 | I38: =F38+G38-H38 -> 0
F39: ='8'!I39 -> 0 | I39: =F39+G39-H39 -> 0
F40: ='8'!I40 -> 0 | I40: =F40+G40-H40 -> 0
E41: Total | F41: =SUM(F22:F40) -> 65836 | G41: =SUM(G22:G40) -> 0 | H41: =SUM(H22:H40) -> 0 | I41: =F41+G41-H41 -> 65836

Sheet 10
A1: EXPENSES
A2: Name | B2: Description | C2: Amount | E2: Commissions | H2: Franchise Owner
E3: Jazz Load | H3: Opening Bal | I3: ='9'!I15 -> 102056
E4: Jazz Cash | K4: Date | L4: Jazz Load | M4: Jazz Cash | N4: Efics MFS | O4: Efics Bill | P4: SIM Commission | Q4: Retail IMSI | R4: Franchise IMSI | S4: GST Comm | T4: Tax Rebate | U4: MNP | V4: Other | W4: Other | X4: TOTAL
E5: Efics MFS | K5: 10 | L5: =F3 -> 0 | M5: =F4 -> 0 | N5: =F5 -> 0 | O5: =F6 -> 0 | P5: =F7 -> 0 | Q5: =F8 -> 0 | R5: =F9 -> 0 | S5: =F10 -> 0 | T5: =F11 -> 0 | U5: =F12 -> 0 | V5: =F13 -> 0 | W5: =F14 -> 0 | X5: =SUM(L5:W5) -> 0
E6: Efics BILL
E7: SIM Commission
E8: Retail IMSI
E9: Franchise IMSI
E10: GST Comm
E11: Tax Claim Rebate
E12: MNP Comm
E13: Other
E14: Other
E15: Total | F15: =SUM(F3:F14) -> 0 | H15: Total | I15: =SUM(I3:I14) -> 102056
E17: Opening Bal | F17: Issue Balance | G17: Total | H17: Expense | I17: Return
E18: ='9'!I18 -> -8104 | F18: =F15 -> 0 | G18: =F18+E18 -> -8104 | H18: =C30 -> 0 | I18: =G18-H18 -> -8104
E20: Credit
E21: Name | F21: Opening | G21: Today | H21: Receive | I21: Balance
F22: ='9'!I22 -> 20126 | I22: =F22+G22-H22 -> 20126
F23: ='9'!I23 -> 410 | I23: =F23+G23-H23 -> 410
F24: ='9'!I24 -> 0 | I24: =F24+G24-H24 -> 0
F25: ='9'!I25 -> 8300 | I25: =F25+G25-H25 -> 8300
F26: ='9'!I26 -> 10000 | I26: =F26+G26-H26 -> 10000
F27: ='9'!I27 -> 20000 | I27: =F27+G27-H27 -> 20000
F28: ='9'!I28 -> 1000 | I28: =F28+G28-H28 -> 1000
F29: ='9'!I29 -> 1000 | I29: =F29+G29-H29 -> 1000
A30: TOTAL | C30: =SUM(C3:C29) -> 0 | F30: ='9'!I30 -> 5000 | I30: =F30+G30-H30 -> 5000
F31: ='9'!I31 -> 0 | I31: =F31+G31-H31 -> 0
F32: ='9'!I32 -> 0 | I32: =F32+G32-H32 -> 0
F33: ='9'!I33 -> 0 | I33: =F33+G33-H33 -> 0
F34: ='9'!I34 -> 0 | I34: =F34+G34-H34 -> 0
F35: ='9'!I35 -> 0 | I35: =F35+G35-H35 -> 0
F36: ='9'!I36 -> 0 | I36: =F36+G36-H36 -> 0
F37: ='9'!I37 -> 0 | I37: =F37+G37-H37 -> 0
F38: ='9'!I38 -> 0 | I38: =F38+G38-H38 -> 0
F39: ='9'!I39 -> 0 | I39: =F39+G39-H39 -> 0
F40: ='9'!I40 -> 0 | I40: =F40+G40-H40 -> 0
E41: Total | F41: =SUM(F22:F40) -> 65836 | G41: =SUM(G22:G40) -> 0 | H41: =SUM(H22:H40) -> 0 | I41: =F41+G41-H41 -> 65836

Sheet 11
A1: EXPENSES
A2: Name | B2: Description | C2: Amount | E2: Commissions | H2: Franchise Owner
E3: Jazz Load | H3: Opening Bal | I3: ='10'!I15 -> 102056
E4: Jazz Cash | K4: Date | L4: Jazz Load | M4: Jazz Cash | N4: Efics MFS | O4: Efics Bill | P4: SIM Commission | Q4: Retail IMSI | R4: Franchise IMSI | S4: GST Comm | T4: Tax Rebate | U4: MNP | V4: Other | W4: Other | X4: TOTAL
E5: Efics MFS | K5: 11 | L5: =F3 -> 0 | M5: =F4 -> 0 | N5: =F5 -> 0 | O5: =F6 -> 0 | P5: =F7 -> 0 | Q5: =F8 -> 0 | R5: =F9 -> 0 | S5: =F10 -> 0 | T5: =F11 -> 0 | U5: =F12 -> 0 | V5: =F13 -> 0 | W5: =F14 -> 0 | X5: =SUM(L5:W5) -> 0
E6: Efics BILL
E7: SIM Commission
E8: Retail IMSI
E9: Franchise IMSI
E10: GST Comm
E11: Tax Claim Rebate
E12: MNP Comm
E13: Other
E14: Other
E15: Total | F15: =SUM(F3:F14) -> 0 | H15: Total | I15: =SUM(I3:I14) -> 102056
E17: Opening Bal | F17: Issue Balance | G17: Total | H17: Expense | I17: Return
E18: ='10'!I18 -> -8104 | F18: =F15 -> 0 | G18: =F18+E18 -> -8104 | H18: =C30 -> 0 | I18: =G18-H18 -> -8104
E20: Credit
E21: Name | F21: Opening | G21: Today | H21: Receive | I21: Balance
F22: ='10'!I22 -> 20126 | I22: =F22+G22-H22 -> 20126
F23: ='10'!I23 -> 410 | I23: =F23+G23-H23 -> 410
F24: ='10'!I24 -> 0 | I24: =F24+G24-H24 -> 0
F25: ='10'!I25 -> 8300 | I25: =F25+G25-H25 -> 8300
F26: ='10'!I26 -> 10000 | I26: =F26+G26-H26 -> 10000
F27: ='10'!I27 -> 20000 | I27: =F27+G27-H27 -> 20000
F28: ='10'!I28 -> 1000 | I28: =F28+G28-H28 -> 1000
F29: ='10'!I29 -> 1000 | I29: =F29+G29-H29 -> 1000
A30: TOTAL | C30: =SUM(C3:C29) -> 0 | F30: ='10'!I30 -> 5000 | I30: =F30+G30-H30 -> 5000
F31: ='10'!I31 -> 0 | I31: =F31+G31-H31 -> 0
F32: ='10'!I32 -> 0 | I32: =F32+G32-H32 -> 0
F33: ='10'!I33 -> 0 | I33: =F33+G33-H33 -> 0
F34: ='10'!I34 -> 0 | I34: =F34+G34-H34 -> 0
F35: ='10'!I35 -> 0 | I35: =F35+G35-H35 -> 0
F36: ='10'!I36 -> 0 | I36: =F36+G36-H36 -> 0
F37: ='10'!I37 -> 0 | I37: =F37+G37-H37 -> 0
F38: ='10'!I38 -> 0 | I38: =F38+G38-H38 -> 0
F39: ='10'!I39 -> 0 | I39: =F39+G39-H39 -> 0
F40: ='10'!I40 -> 0 | I40: =F40+G40-H40 -> 0
E41: Total | F41: =SUM(F22:F40) -> 65836 | G41: =SUM(G22:G40) -> 0 | H41: =SUM(H22:H40) -> 0 | I41: =F41+G41-H41 -> 65836

Sheet 12
A1: EXPENSES
A2: Name | B2: Description | C2: Amount | E2: Commissions | H2: Franchise Owner
E3: Jazz Load | H3: Opening Bal | I3: ='11'!I15 -> 102056
E4: Jazz Cash | K4: Date | L4: Jazz Load | M4: Jazz Cash | N4: Efics MFS | O4: Efics Bill | P4: SIM Commission | Q4: Retail IMSI | R4: Franchise IMSI | S4: GST Comm | T4: Tax Rebate | U4: MNP | V4: Other | W4: Other | X4: TOTAL
E5: Efics MFS | K5: 12 | L5: =F3 -> 0 | M5: =F4 -> 0 | N5: =F5 -> 0 | O5: =F6 -> 0 | P5: =F7 -> 0 | Q5: =F8 -> 0 | R5: =F9 -> 0 | S5: =F10 -> 0 | T5: =F11 -> 0 | U5: =F12 -> 0 | V5: =F13 -> 0 | W5: =F14 -> 0 | X5: =SUM(L5:W5) -> 0
E6: Efics BILL
E7: SIM Commission
E8: Retail IMSI
E9: Franchise IMSI
E10: GST Comm
E11: Tax Claim Rebate
E12: MNP Comm
E13: Other
E14: Other
E15: Total | F15: =SUM(F3:F14) -> 0 | H15: Total | I15: =SUM(I3:I14) -> 102056
E17: Opening Bal | F17: Issue Balance | G17: Total | H17: Expense | I17: Return
E18: ='11'!I18 -> -8104 | F18: =F15 -> 0 | G18: =F18+E18 -> -8104 | H18: =C30 -> 0 | I18: =G18-H18 -> -8104
E20: Credit
E21: Name | F21: Opening | G21: Today | H21: Receive | I21: Balance
F22: ='11'!I22 -> 20126 | I22: =F22+G22-H22 -> 20126
F23: ='11'!I23 -> 410 | I23: =F23+G23-H23 -> 410
F24: ='11'!I24 -> 0 | I24: =F24+G24-H24 -> 0
F25: ='11'!I25 -> 8300 | I25: =F25+G25-H25 -> 8300
F26: ='11'!I26 -> 10000 | I26: =F26+G26-H26 -> 10000
F27: ='11'!I27 -> 20000 | I27: =F27+G27-H27 -> 20000
F28: ='11'!I28 -> 1000 | I28: =F28+G28-H28 -> 1000
F29: ='11'!I29 -> 1000 | I29: =F29+G29-H29 -> 1000
A30: TOTAL | C30: =SUM(C3:C29) -> 0 | F30: ='11'!I30 -> 5000 | I30: =F30+G30-H30 -> 5000
F31: ='11'!I31 -> 0 | I31: =F31+G31-H31 -> 0
F32: ='11'!I32 -> 0 | I32: =F32+G32-H32 -> 0
F33: ='11'!I33 -> 0 | I33: =F33+G33-H33 -> 0
F34: ='11'!I34 -> 0 | I34: =F34+G34-H34 -> 0
F35: ='11'!I35 -> 0 | I35: =F35+G35-H35 -> 0
F36: ='11'!I36 -> 0 | I36: =F36+G36-H36 -> 0
F37: ='11'!I37 -> 0 | I37: =F37+G37-H37 -> 0
F38: ='11'!I38 -> 0 | I38: =F38+G38-H38 -> 0
F39: ='11'!I39 -> 0 | I39: =F39+G39-H39 -> 0
F40: ='11'!I40 -> 0 | I40: =F40+G40-H40 -> 0
E41: Total | F41: =SUM(F22:F40) -> 65836 | G41: =SUM(G22:G40) -> 0 | H41: =SUM(H22:H40) -> 0 | I41: =F41+G41-H41 -> 65836

Sheet 13
A1: EXPENSES
A2: Name | B2: Description | C2: Amount | E2: Commissions | H2: Franchise Owner
E3: Jazz Load | H3: Opening Bal | I3: ='12'!I15 -> 102056
E4: Jazz Cash | K4: Date | L4: Jazz Load | M4: Jazz Cash | N4: Efics MFS | O4: Efics Bill | P4: SIM Commission | Q4: Retail IMSI | R4: Franchise IMSI | S4: GST Comm | T4: Tax Rebate | U4: MNP | V4: Other | W4: Other | X4: TOTAL
E5: Efics MFS | K5: 13 | L5: =F3 -> 0 | M5: =F4 -> 0 | N5: =F5 -> 0 | O5: =F6 -> 0 | P5: =F7 -> 0 | Q5: =F8 -> 0 | R5: =F9 -> 0 | S5: =F10 -> 0 | T5: =F11 -> 0 | U5: =F12 -> 0 | V5: =F13 -> 0 | W5: =F14 -> 0 | X5: =SUM(L5:W5) -> 0
E6: Efics BILL
E7: SIM Commission
E8: Retail IMSI
E9: Franchise IMSI
E10: GST Comm
E11: Tax Claim Rebate
E12: MNP Comm
E13: Other
E14: Other
E15: Total | F15: =SUM(F3:F14) -> 0 | H15: Total | I15: =SUM(I3:I14) -> 102056
E17: Opening Bal | F17: Issue Balance | G17: Total | H17: Expense | I17: Return
E18: ='12'!I18 -> -8104 | F18: =F15 -> 0 | G18: =F18+E18 -> -8104 | H18: =C30 -> 0 | I18: =G18-H18 -> -8104
E20: Credit
E21: Name | F21: Opening | G21: Today | H21: Receive | I21: Balance
F22: ='12'!I22 -> 20126 | I22: =F22+G22-H22 -> 20126
F23: ='12'!I23 -> 410 | I23: =F23+G23-H23 -> 410
F24: ='12'!I24 -> 0 | I24: =F24+G24-H24 -> 0
F25: ='12'!I25 -> 8300 | I25: =F25+G25-H25 -> 8300
F26: ='12'!I26 -> 10000 | I26: =F26+G26-H26 -> 10000
F27: ='12'!I27 -> 20000 | I27: =F27+G27-H27 -> 20000
F28: ='12'!I28 -> 1000 | I28: =F28+G28-H28 -> 1000
F29: ='12'!I29 -> 1000 | I29: =F29+G29-H29 -> 1000
A30: TOTAL | C30: =SUM(C3:C29) -> 0 | F30: ='12'!I30 -> 5000 | I30: =F30+G30-H30 -> 5000
F31: ='12'!I31 -> 0 | I31: =F31+G31-H31 -> 0
F32: ='12'!I32 -> 0 | I32: =F32+G32-H32 -> 0
F33: ='12'!I33 -> 0 | I33: =F33+G33-H33 -> 0
F34: ='12'!I34 -> 0 | I34: =F34+G34-H34 -> 0
F35: ='12'!I35 -> 0 | I35: =F35+G35-H35 -> 0
F36: ='12'!I36 -> 0 | I36: =F36+G36-H36 -> 0
F37: ='12'!I37 -> 0 | I37: =F37+G37-H37 -> 0
F38: ='12'!I38 -> 0 | I38: =F38+G38-H38 -> 0
F39: ='12'!I39 -> 0 | I39: =F39+G39-H39 -> 0
F40: ='12'!I40 -> 0 | I40: =F40+G40-H40 -> 0
E41: Total | F41: =SUM(F22:F40) -> 65836 | G41: =SUM(G22:G40) -> 0 | H41: =SUM(H22:H40) -> 0 | I41: =F41+G41-H41 -> 65836

Sheet 14
A1: EXPENSES
A2: Name | B2: Description | C2: Amount | E2: Commissions | H2: Franchise Owner
E3: Jazz Load | H3: Opening Bal | I3: ='13'!I15 -> 102056
E4: Jazz Cash | K4: Date | L4: Jazz Load | M4: Jazz Cash | N4: Efics MFS | O4: Efics Bill | P4: SIM Commission | Q4: Retail IMSI | R4: Franchise IMSI | S4: GST Comm | T4: Tax Rebate | U4: MNP | V4: Other | W4: Other | X4: TOTAL
E5: Efics MFS | K5: 14 | L5: =F3 -> 0 | M5: =F4 -> 0 | N5: =F5 -> 0 | O5: =F6 -> 0 | P5: =F7 -> 0 | Q5: =F8 -> 0 | R5: =F9 -> 0 | S5: =F10 -> 0 | T5: =F11 -> 0 | U5: =F12 -> 0 | V5: =F13 -> 0 | W5: =F14 -> 0 | X5: =SUM(L5:W5) -> 0
E6: Efics BILL
E7: SIM Commission
E8: Retail IMSI
E9: Franchise IMSI
E10: GST Comm
E11: Tax Claim Rebate
E12: MNP Comm
E13: Other
E14: Other
E15: Total | F15: =SUM(F3:F14) -> 0 | H15: Total | I15: =SUM(I3:I14) -> 102056
E17: Opening Bal | F17: Issue Balance | G17: Total | H17: Expense | I17: Return
E18: ='13'!I18 -> -8104 | F18: =F15 -> 0 | G18: =F18+E18 -> -8104 | H18: =C30 -> 0 | I18: =G18-H18 -> -8104
E20: Credit
E21: Name | F21: Opening | G21: Today | H21: Receive | I21: Balance
F22: ='13'!I22 -> 20126 | I22: =F22+G22-H22 -> 20126
F23: ='13'!I23 -> 410 | I23: =F23+G23-H23 -> 410
F24: ='13'!I24 -> 0 | I24: =F24+G24-H24 -> 0
F25: ='13'!I25 -> 8300 | I25: =F25+G25-H25 -> 8300
F26: ='13'!I26 -> 10000 | I26: =F26+G26-H26 -> 10000
F27: ='13'!I27 -> 20000 | I27: =F27+G27-H27 -> 20000
F28: ='13'!I28 -> 1000 | I28: =F28+G28-H28 -> 1000
F29: ='13'!I29 -> 1000 | I29: =F29+G29-H29 -> 1000
A30: TOTAL | C30: =SUM(C3:C29) -> 0 | F30: ='13'!I30 -> 5000 | I30: =F30+G30-H30 -> 5000
F31: ='13'!I31 -> 0 | I31: =F31+G31-H31 -> 0
F32: ='13'!I32 -> 0 | I32: =F32+G32-H32 -> 0
F33: ='13'!I33 -> 0 | I33: =F33+G33-H33 -> 0
F34: ='13'!I34 -> 0 | I34: =F34+G34-H34 -> 0
F35: ='13'!I35 -> 0 | I35: =F35+G35-H35 -> 0
F36: ='13'!I36 -> 0 | I36: =F36+G36-H36 -> 0
F37: ='13'!I37 -> 0 | I37: =F37+G37-H37 -> 0
F38: ='13'!I38 -> 0 | I38: =F38+G38-H38 -> 0
F39: ='13'!I39 -> 0 | I39: =F39+G39-H39 -> 0
F40: ='13'!I40 -> 0 | I40: =F40+G40-H40 -> 0
E41: Total | F41: =SUM(F22:F40) -> 65836 | G41: =SUM(G22:G40) -> 0 | H41: =SUM(H22:H40) -> 0 | I41: =F41+G41-H41 -> 65836

Sheet 15
A1: EXPENSES
A2: Name | B2: Description | C2: Amount | E2: Commissions | H2: Franchise Owner
E3: Jazz Load | H3: Opening Bal | I3: ='14'!I15 -> 102056
E4: Jazz Cash | K4: Date | L4: Jazz Load | M4: Jazz Cash | N4: Efics MFS | O4: Efics Bill | P4: SIM Commission | Q4: Retail IMSI | R4: Franchise IMSI | S4: GST Comm | T4: Tax Rebate | U4: MNP | V4: Other | W4: Other | X4: TOTAL
E5: Efics MFS | K5: 15 | L5: =F3 -> 0 | M5: =F4 -> 0 | N5: =F5 -> 0 | O5: =F6 -> 0 | P5: =F7 -> 0 | Q5: =F8 -> 0 | R5: =F9 -> 0 | S5: =F10 -> 0 | T5: =F11 -> 0 | U5: =F12 -> 0 | V5: =F13 -> 0 | W5: =F14 -> 0 | X5: =SUM(L5:W5) -> 0
E6: Efics BILL
E7: SIM Commission
E8: Retail IMSI
E9: Franchise IMSI
E10: GST Comm
E11: Tax Claim Rebate
E12: MNP Comm
E13: Other
E14: Other
E15: Total | F15: =SUM(F3:F14) -> 0 | H15: Total | I15: =SUM(I3:I14) -> 102056
E17: Opening Bal | F17: Issue Balance | G17: Total | H17: Expense | I17: Return
E18: ='14'!I18 -> -8104 | F18: =F15 -> 0 | G18: =F18+E18 -> -8104 | H18: =C30 -> 0 | I18: =G18-H18 -> -8104
E20: Credit
E21: Name | F21: Opening | G21: Today | H21: Receive | I21: Balance
F22: ='14'!I22 -> 20126 | I22: =F22+G22-H22 -> 20126
F23: ='14'!I23 -> 410 | I23: =F23+G23-H23 -> 410
F24: ='14'!I24 -> 0 | I24: =F24+G24-H24 -> 0
F25: ='14'!I25 -> 8300 | I25: =F25+G25-H25 -> 8300
F26: ='14'!I26 -> 10000 | I26: =F26+G26-H26 -> 10000
F27: ='14'!I27 -> 20000 | I27: =F27+G27-H27 -> 20000
F28: ='14'!I28 -> 1000 | I28: =F28+G28-H28 -> 1000
F29: ='14'!I29 -> 1000 | I29: =F29+G29-H29 -> 1000
A30: TOTAL | C30: =SUM(C3:C29) -> 0 | F30: ='14'!I30 -> 5000 | I30: =F30+G30-H30 -> 5000
F31: ='14'!I31 -> 0 | I31: =F31+G31-H31 -> 0
F32: ='14'!I32 -> 0 | I32: =F32+G32-H32 -> 0
F33: ='14'!I33 -> 0 | I33: =F33+G33-H33 -> 0
F34: ='14'!I34 -> 0 | I34: =F34+G34-H34 -> 0
F35: ='14'!I35 -> 0 | I35: =F35+G35-H35 -> 0
F36: ='14'!I36 -> 0 | I36: =F36+G36-H36 -> 0
F37: ='14'!I37 -> 0 | I37: =F37+G37-H37 -> 0
F38: ='14'!I38 -> 0 | I38: =F38+G38-H38 -> 0
F39: ='14'!I39 -> 0 | I39: =F39+G39-H39 -> 0
F40: ='14'!I40 -> 0 | I40: =F40+G40-H40 -> 0
E41: Total | F41: =SUM(F22:F40) -> 65836 | G41: =SUM(G22:G40) -> 0 | H41: =SUM(H22:H40) -> 0 | I41: =F41+G41-H41 -> 65836

Sheet 16
A1: EXPENSES
A2: Name | B2: Description | C2: Amount | E2: Commissions | H2: Franchise Owner
E3: Jazz Load | H3: Opening Bal | I3: ='15'!I15 -> 102056
E4: Jazz Cash | K4: Date | L4: Jazz Load | M4: Jazz Cash | N4: Efics MFS | O4: Efics Bill | P4: SIM Commission | Q4: Retail IMSI | R4: Franchise IMSI | S4: GST Comm | T4: Tax Rebate | U4: MNP | V4: Other | W4: Other | X4: TOTAL
E5: Efics MFS | K5: 16 | L5: =F3 -> 0 | M5: =F4 -> 0 | N5: =F5 -> 0 | O5: =F6 -> 0 | P5: =F7 -> 0 | Q5: =F8 -> 0 | R5: =F9 -> 0 | S5: =F10 -> 0 | T5: =F11 -> 0 | U5: =F12 -> 0 | V5: =F13 -> 0 | W5: =F14 -> 0 | X5: =SUM(L5:W5) -> 0
E6: Efics BILL
E7: SIM Commission
E8: Retail IMSI
E9: Franchise IMSI
E10: GST Comm
E11: Tax Claim Rebate
E12: MNP Comm
E13: Other
E14: Other
E15: Total | F15: =SUM(F3:F14) -> 0 | H15: Total | I15: =SUM(I3:I14) -> 102056
E17: Opening Bal | F17: Issue Balance | G17: Total | H17: Expense | I17: Return
E18: ='15'!I18 -> -8104 | F18: =F15 -> 0 | G18: =F18+E18 -> -8104 | H18: =C30 -> 0 | I18: =G18-H18 -> -8104
E20: Credit
E21: Name | F21: Opening | G21: Today | H21: Receive | I21: Balance
F22: ='15'!I22 -> 20126 | I22: =F22+G22-H22 -> 20126
F23: ='15'!I23 -> 410 | I23: =F23+G23-H23 -> 410
F24: ='15'!I24 -> 0 | I24: =F24+G24-H24 -> 0
F25: ='15'!I25 -> 8300 | I25: =F25+G25-H25 -> 8300
F26: ='15'!I26 -> 10000 | I26: =F26+G26-H26 -> 10000
F27: ='15'!I27 -> 20000 | I27: =F27+G27-H27 -> 20000
F28: ='15'!I28 -> 1000 | I28: =F28+G28-H28 -> 1000
F29: ='15'!I29 -> 1000 | I29: =F29+G29-H29 -> 1000
A30: TOTAL | C30: =SUM(C3:C29) -> 0 | F30: ='15'!I30 -> 5000 | I30: =F30+G30-H30 -> 5000
F31: ='15'!I31 -> 0 | I31: =F31+G31-H31 -> 0
F32: ='15'!I32 -> 0 | I32: =F32+G32-H32 -> 0
F33: ='15'!I33 -> 0 | I33: =F33+G33-H33 -> 0
F34: ='15'!I34 -> 0 | I34: =F34+G34-H34 -> 0
F35: ='15'!I35 -> 0 | I35: =F35+G35-H35 -> 0
F36: ='15'!I36 -> 0 | I36: =F36+G36-H36 -> 0
F37: ='15'!I37 -> 0 | I37: =F37+G37-H37 -> 0
F38: ='15'!I38 -> 0 | I38: =F38+G38-H38 -> 0
F39: ='15'!I39 -> 0 | I39: =F39+G39-H39 -> 0
F40: ='15'!I40 -> 0 | I40: =F40+G40-H40 -> 0
E41: Total | F41: =SUM(F22:F40) -> 65836 | G41: =SUM(G22:G40) -> 0 | H41: =SUM(H22:H40) -> 0 | I41: =F41+G41-H41 -> 65836

Sheet 17
A1: EXPENSES
A2: Name | B2: Description | C2: Amount | E2: Commissions | H2: Franchise Owner
E3: Jazz Load | H3: Opening Bal | I3: ='16'!I15 -> 102056
E4: Jazz Cash | K4: Date | L4: Jazz Load | M4: Jazz Cash | N4: Efics MFS | O4: Efics Bill | P4: SIM Commission | Q4: Retail IMSI | R4: Franchise IMSI | S4: GST Comm | T4: Tax Rebate | U4: MNP | V4: Other | W4: Other | X4: TOTAL
E5: Efics MFS | K5: 17 | L5: =F3 -> 0 | M5: =F4 -> 0 | N5: =F5 -> 0 | O5: =F6 -> 0 | P5: =F7 -> 0 | Q5: =F8 -> 0 | R5: =F9 -> 0 | S5: =F10 -> 0 | T5: =F11 -> 0 | U5: =F12 -> 0 | V5: =F13 -> 0 | W5: =F14 -> 0 | X5: =SUM(L5:W5) -> 0
E6: Efics BILL
E7: SIM Commission
E8: Retail IMSI
E9: Franchise IMSI
E10: GST Comm
E11: Tax Claim Rebate
E12: MNP Comm
E13: Other
E14: Other
E15: Total | F15: =SUM(F3:F14) -> 0 | H15: Total | I15: =SUM(I3:I14) -> 102056
E17: Opening Bal | F17: Issue Balance | G17: Total | H17: Expense | I17: Return
E18: ='16'!I18 -> -8104 | F18: =F15 -> 0 | G18: =F18+E18 -> -8104 | H18: =C30 -> 0 | I18: =G18-H18 -> -8104
E20: Credit
E21: Name | F21: Opening | G21: Today | H21: Receive | I21: Balance
F22: ='16'!I22 -> 20126 | I22: =F22+G22-H22 -> 20126
F23: ='16'!I23 -> 410 | I23: =F23+G23-H23 -> 410
F24: ='16'!I24 -> 0 | I24: =F24+G24-H24 -> 0
F25: ='16'!I25 -> 8300 | I25: =F25+G25-H25 -> 8300
F26: ='16'!I26 -> 10000 | I26: =F26+G26-H26 -> 10000
F27: ='16'!I27 -> 20000 | I27: =F27+G27-H27 -> 20000
F28: ='16'!I28 -> 1000 | I28: =F28+G28-H28 -> 1000
F29: ='16'!I29 -> 1000 | I29: =F29+G29-H29 -> 1000
A30: TOTAL | C30: =SUM(C3:C29) -> 0 | F30: ='16'!I30 -> 5000 | I30: =F30+G30-H30 -> 5000
F31: ='16'!I31 -> 0 | I31: =F31+G31-H31 -> 0
F32: ='16'!I32 -> 0 | I32: =F32+G32-H32 -> 0
F33: ='16'!I33 -> 0 | I33: =F33+G33-H33 -> 0
F34: ='16'!I34 -> 0 | I34: =F34+G34-H34 -> 0
F35: ='16'!I35 -> 0 | I35: =F35+G35-H35 -> 0
F36: ='16'!I36 -> 0 | I36: =F36+G36-H36 -> 0
F37: ='16'!I37 -> 0 | I37: =F37+G37-H37 -> 0
F38: ='16'!I38 -> 0 | I38: =F38+G38-H38 -> 0
F39: ='16'!I39 -> 0 | I39: =F39+G39-H39 -> 0
F40: ='16'!I40 -> 0 | I40: =F40+G40-H40 -> 0
E41: Total | F41: =SUM(F22:F40) -> 65836 | G41: =SUM(G22:G40) -> 0 | H41: =SUM(H22:H40) -> 0 | I41: =F41+G41-H41 -> 65836

Sheet 18
A1: EXPENSES
A2: Name | B2: Description | C2: Amount | E2: Commissions | H2: Franchise Owner
E3: Jazz Load | H3: Opening Bal | I3: ='17'!I15 -> 102056
E4: Jazz Cash | K4: Date | L4: Jazz Load | M4: Jazz Cash | N4: Efics MFS | O4: Efics Bill | P4: SIM Commission | Q4: Retail IMSI | R4: Franchise IMSI | S4: GST Comm | T4: Tax Rebate | U4: MNP | V4: Other | W4: Other | X4: TOTAL
E5: Efics MFS | K5: 18 | L5: =F3 -> 0 | M5: =F4 -> 0 | N5: =F5 -> 0 | O5: =F6 -> 0 | P5: =F7 -> 0 | Q5: =F8 -> 0 | R5: =F9 -> 0 | S5: =F10 -> 0 | T5: =F11 -> 0 | U5: =F12 -> 0 | V5: =F13 -> 0 | W5: =F14 -> 0 | X5: =SUM(L5:W5) -> 0
E6: Efics BILL
E7: SIM Commission
E8: Retail IMSI
E9: Franchise IMSI
E10: GST Comm
E11: Tax Claim Rebate
E12: MNP Comm
E13: Other
E14: Other
E15: Total | F15: =SUM(F3:F14) -> 0 | H15: Total | I15: =SUM(I3:I14) -> 102056
E17: Opening Bal | F17: Issue Balance | G17: Total | H17: Expense | I17: Return
E18: ='17'!I18 -> -8104 | F18: =F15 -> 0 | G18: =F18+E18 -> -8104 | H18: =C30 -> 0 | I18: =G18-H18 -> -8104
E20: Credit
E21: Name | F21: Opening | G21: Today | H21: Receive | I21: Balance
F22: ='17'!I22 -> 20126 | I22: =F22+G22-H22 -> 20126
F23: ='17'!I23 -> 410 | I23: =F23+G23-H23 -> 410
F24: ='17'!I24 -> 0 | I24: =F24+G24-H24 -> 0
F25: ='17'!I25 -> 8300 | I25: =F25+G25-H25 -> 8300
F26: ='17'!I26 -> 10000 | I26: =F26+G26-H26 -> 10000
F27: ='17'!I27 -> 20000 | I27: =F27+G27-H27 -> 20000
F28: ='17'!I28 -> 1000 | I28: =F28+G28-H28 -> 1000
F29: ='17'!I29 -> 1000 | I29: =F29+G29-H29 -> 1000
A30: TOTAL | C30: =SUM(C3:C29) -> 0 | F30: ='17'!I30 -> 5000 | I30: =F30+G30-H30 -> 5000
F31: ='17'!I31 -> 0 | I31: =F31+G31-H31 -> 0
F32: ='17'!I32 -> 0 | I32: =F32+G32-H32 -> 0
F33: ='17'!I33 -> 0 | I33: =F33+G33-H33 -> 0
F34: ='17'!I34 -> 0 | I34: =F34+G34-H34 -> 0
F35: ='17'!I35 -> 0 | I35: =F35+G35-H35 -> 0
F36: ='17'!I36 -> 0 | I36: =F36+G36-H36 -> 0
F37: ='17'!I37 -> 0 | I37: =F37+G37-H37 -> 0
F38: ='17'!I38 -> 0 | I38: =F38+G38-H38 -> 0
F39: ='17'!I39 -> 0 | I39: =F39+G39-H39 -> 0
F40: ='17'!I40 -> 0 | I40: =F40+G40-H40 -> 0
E41: Total | F41: =SUM(F22:F40) -> 65836 | G41: =SUM(G22:G40) -> 0 | H41: =SUM(H22:H40) -> 0 | I41: =F41+G41-H41 -> 65836

Sheet 19
A1: EXPENSES
A2: Name | B2: Description | C2: Amount | E2: Commissions | H2: Franchise Owner
E3: Jazz Load | H3: Opening Bal | I3: ='18'!I15 -> 102056
E4: Jazz Cash | K4: Date | L4: Jazz Load | M4: Jazz Cash | N4: Efics MFS | O4: Efics Bill | P4: SIM Commission | Q4: Retail IMSI | R4: Franchise IMSI | S4: GST Comm | T4: Tax Rebate | U4: MNP | V4: Other | W4: Other | X4: TOTAL
E5: Efics MFS | K5: 19 | L5: =F3 -> 0 | M5: =F4 -> 0 | N5: =F5 -> 0 | O5: =F6 -> 0 | P5: =F7 -> 0 | Q5: =F8 -> 0 | R5: =F9 -> 0 | S5: =F10 -> 0 | T5: =F11 -> 0 | U5: =F12 -> 0 | V5: =F13 -> 0 | W5: =F14 -> 0 | X5: =SUM(L5:W5) -> 0
E6: Efics BILL
E7: SIM Commission
E8: Retail IMSI
E9: Franchise IMSI
E10: GST Comm
E11: Tax Claim Rebate
E12: MNP Comm
E13: Other
E14: Other
E15: Total | F15: =SUM(F3:F14) -> 0 | H15: Total | I15: =SUM(I3:I14) -> 102056
E17: Opening Bal | F17: Issue Balance | G17: Total | H17: Expense | I17: Return
E18: ='18'!I18 -> -8104 | F18: =F15 -> 0 | G18: =F18+E18 -> -8104 | H18: =C30 -> 0 | I18: =G18-H18 -> -8104
E20: Credit
E21: Name | F21: Opening | G21: Today | H21: Receive | I21: Balance
F22: ='18'!I22 -> 20126 | I22: =F22+G22-H22 -> 20126
F23: ='18'!I23 -> 410 | I23: =F23+G23-H23 -> 410
F24: ='18'!I24 -> 0 | I24: =F24+G24-H24 -> 0
F25: ='18'!I25 -> 8300 | I25: =F25+G25-H25 -> 8300
F26: ='18'!I26 -> 10000 | I26: =F26+G26-H26 -> 10000
F27: ='18'!I27 -> 20000 | I27: =F27+G27-H27 -> 20000
F28: ='18'!I28 -> 1000 | I28: =F28+G28-H28 -> 1000
F29: ='18'!I29 -> 1000 | I29: =F29+G29-H29 -> 1000
A30: TOTAL | C30: =SUM(C3:C29) -> 0 | F30: ='18'!I30 -> 5000 | I30: =F30+G30-H30 -> 5000
F31: ='18'!I31 -> 0 | I31: =F31+G31-H31 -> 0
F32: ='18'!I32 -> 0 | I32: =F32+G32-H32 -> 0
F33: ='18'!I33 -> 0 | I33: =F33+G33-H33 -> 0
F34: ='18'!I34 -> 0 | I34: =F34+G34-H34 -> 0
F35: ='18'!I35 -> 0 | I35: =F35+G35-H35 -> 0
F36: ='18'!I36 -> 0 | I36: =F36+G36-H36 -> 0
F37: ='18'!I37 -> 0 | I37: =F37+G37-H37 -> 0
F38: ='18'!I38 -> 0 | I38: =F38+G38-H38 -> 0
F39: ='18'!I39 -> 0 | I39: =F39+G39-H39 -> 0
F40: ='18'!I40 -> 0 | I40: =F40+G40-H40 -> 0
E41: Total | F41: =SUM(F22:F40) -> 65836 | G41: =SUM(G22:G40) -> 0 | H41: =SUM(H22:H40) -> 0 | I41: =F41+G41-H41 -> 65836

Sheet 20
A1: EXPENSES
A2: Name | B2: Description | C2: Amount | E2: Commissions | H2: Franchise Owner
E3: Jazz Load | H3: Opening Bal | I3: ='19'!I15 -> 102056
E4: Jazz Cash | K4: Date | L4: Jazz Load | M4: Jazz Cash | N4: Efics MFS | O4: Efics Bill | P4: SIM Commission | Q4: Retail IMSI | R4: Franchise IMSI | S4: GST Comm | T4: Tax Rebate | U4: MNP | V4: Other | W4: Other | X4: TOTAL
E5: Efics MFS | K5: 20 | L5: =F3 -> 0 | M5: =F4 -> 0 | N5: =F5 -> 0 | O5: =F6 -> 0 | P5: =F7 -> 0 | Q5: =F8 -> 0 | R5: =F9 -> 0 | S5: =F10 -> 0 | T5: =F11 -> 0 | U5: =F12 -> 0 | V5: =F13 -> 0 | W5: =F14 -> 0 | X5: =SUM(L5:W5) -> 0
E6: Efics BILL
E7: SIM Commission
E8: Retail IMSI
E9: Franchise IMSI
E10: GST Comm
E11: Tax Claim Rebate
E12: MNP Comm
E13: Other
E14: Other
E15: Total | F15: =SUM(F3:F14) -> 0 | H15: Total | I15: =SUM(I3:I14) -> 102056
E17: Opening Bal | F17: Issue Balance | G17: Total | H17: Expense | I17: Return
E18: ='19'!I18 -> -8104 | F18: =F15 -> 0 | G18: =F18+E18 -> -8104 | H18: =C30 -> 0 | I18: =G18-H18 -> -8104
E20: Credit
E21: Name | F21: Opening | G21: Today | H21: Receive | I21: Balance
F22: ='19'!I22 -> 20126 | I22: =F22+G22-H22 -> 20126
F23: ='19'!I23 -> 410 | I23: =F23+G23-H23 -> 410
F24: ='19'!I24 -> 0 | I24: =F24+G24-H24 -> 0
F25: ='19'!I25 -> 8300 | I25: =F25+G25-H25 -> 8300
F26: ='19'!I26 -> 10000 | I26: =F26+G26-H26 -> 10000
F27: ='19'!I27 -> 20000 | I27: =F27+G27-H27 -> 20000
F28: ='19'!I28 -> 1000 | I28: =F28+G28-H28 -> 1000
F29: ='19'!I29 -> 1000 | I29: =F29+G29-H29 -> 1000
A30: TOTAL | C30: =SUM(C3:C29) -> 0 | F30: ='19'!I30 -> 5000 | I30: =F30+G30-H30 -> 5000
F31: ='19'!I31 -> 0 | I31: =F31+G31-H31 -> 0
F32: ='19'!I32 -> 0 | I32: =F32+G32-H32 -> 0
F33: ='19'!I33 -> 0 | I33: =F33+G33-H33 -> 0
F34: ='19'!I34 -> 0 | I34: =F34+G34-H34 -> 0
F35: ='19'!I35 -> 0 | I35: =F35+G35-H35 -> 0
F36: ='19'!I36 -> 0 | I36: =F36+G36-H36 -> 0
F37: ='19'!I37 -> 0 | I37: =F37+G37-H37 -> 0
F38: ='19'!I38 -> 0 | I38: =F38+G38-H38 -> 0
F39: ='19'!I39 -> 0 | I39: =F39+G39-H39 -> 0
F40: ='19'!I40 -> 0 | I40: =F40+G40-H40 -> 0
E41: Total | F41: =SUM(F22:F40) -> 65836 | G41: =SUM(G22:G40) -> 0 | H41: =SUM(H22:H40) -> 0 | I41: =F41+G41-H41 -> 65836

Sheet 21
A1: EXPENSES
A2: Name | B2: Description | C2: Amount | E2: Commissions | H2: Franchise Owner
E3: Jazz Load | H3: Opening Bal | I3: ='20'!I15 -> 102056
E4: Jazz Cash | K4: Date | L4: Jazz Load | M4: Jazz Cash | N4: Efics MFS | O4: Efics Bill | P4: SIM Commission | Q4: Retail IMSI | R4: Franchise IMSI | S4: GST Comm | T4: Tax Rebate | U4: MNP | V4: Other | W4: Other | X4: TOTAL
E5: Efics MFS | K5: 21 | L5: =F3 -> 0 | M5: =F4 -> 0 | N5: =F5 -> 0 | O5: =F6 -> 0 | P5: =F7 -> 0 | Q5: =F8 -> 0 | R5: =F9 -> 0 | S5: =F10 -> 0 | T5: =F11 -> 0 | U5: =F12 -> 0 | V5: =F13 -> 0 | W5: =F14 -> 0 | X5: =SUM(L5:W5) -> 0
E6: Efics BILL
E7: SIM Commission
E8: Retail IMSI
E9: Franchise IMSI
E10: GST Comm
E11: Tax Claim Rebate
E12: MNP Comm
E13: Other
E14: Other
E15: Total | F15: =SUM(F3:F14) -> 0 | H15: Total | I15: =SUM(I3:I14) -> 102056
E17: Opening Bal | F17: Issue Balance | G17: Total | H17: Expense | I17: Return
E18: ='20'!I18 -> -8104 | F18: =F15 -> 0 | G18: =F18+E18 -> -8104 | H18: =C30 -> 0 | I18: =G18-H18 -> -8104
E20: Credit
E21: Name | F21: Opening | G21: Today | H21: Receive | I21: Balance
F22: ='20'!I22 -> 20126 | I22: =F22+G22-H22 -> 20126
F23: ='20'!I23 -> 410 | I23: =F23+G23-H23 -> 410
F24: ='20'!I24 -> 0 | I24: =F24+G24-H24 -> 0
F25: ='20'!I25 -> 8300 | I25: =F25+G25-H25 -> 8300
F26: ='20'!I26 -> 10000 | I26: =F26+G26-H26 -> 10000
F27: ='20'!I27 -> 20000 | I27: =F27+G27-H27 -> 20000
F28: ='20'!I28 -> 1000 | I28: =F28+G28-H28 -> 1000
F29: ='20'!I29 -> 1000 | I29: =F29+G29-H29 -> 1000
A30: TOTAL | C30: =SUM(C3:C29) -> 0 | F30: ='20'!I30 -> 5000 | I30: =F30+G30-H30 -> 5000
F31: ='20'!I31 -> 0 | I31: =F31+G31-H31 -> 0
F32: ='20'!I32 -> 0 | I32: =F32+G32-H32 -> 0
F33: ='20'!I33 -> 0 | I33: =F33+G33-H33 -> 0
F34: ='20'!I34 -> 0 | I34: =F34+G34-H34 -> 0
F35: ='20'!I35 -> 0 | I35: =F35+G35-H35 -> 0
F36: ='20'!I36 -> 0 | I36: =F36+G36-H36 -> 0
F37: ='20'!I37 -> 0 | I37: =F37+G37-H37 -> 0
F38: ='20'!I38 -> 0 | I38: =F38+G38-H38 -> 0
F39: ='20'!I39 -> 0 | I39: =F39+G39-H39 -> 0
F40: ='20'!I40 -> 0 | I40: =F40+G40-H40 -> 0
E41: Total | F41: =SUM(F22:F40) -> 65836 | G41: =SUM(G22:G40) -> 0 | H41: =SUM(H22:H40) -> 0 | I41: =F41+G41-H41 -> 65836

Sheet 22
A1: EXPENSES
A2: Name | B2: Description | C2: Amount | E2: Commissions | H2: Franchise Owner
E3: Jazz Load | H3: Opening Bal | I3: ='21'!I15 -> 102056
E4: Jazz Cash | K4: Date | L4: Jazz Load | M4: Jazz Cash | N4: Efics MFS | O4: Efics Bill | P4: SIM Commission | Q4: Retail IMSI | R4: Franchise IMSI | S4: GST Comm | T4: Tax Rebate | U4: MNP | V4: Other | W4: Other | X4: TOTAL
E5: Efics MFS | K5: 22 | L5: =F3 -> 0 | M5: =F4 -> 0 | N5: =F5 -> 0 | O5: =F6 -> 0 | P5: =F7 -> 0 | Q5: =F8 -> 0 | R5: =F9 -> 0 | S5: =F10 -> 0 | T5: =F11 -> 0 | U5: =F12 -> 0 | V5: =F13 -> 0 | W5: =F14 -> 0 | X5: =SUM(L5:W5) -> 0
E6: Efics BILL
E7: SIM Commission
E8: Retail IMSI
E9: Franchise IMSI
E10: GST Comm
E11: Tax Claim Rebate
E12: MNP Comm
E13: Other
E14: Other
E15: Total | F15: =SUM(F3:F14) -> 0 | H15: Total | I15: =SUM(I3:I14) -> 102056
E17: Opening Bal | F17: Issue Balance | G17: Total | H17: Expense | I17: Return
E18: ='21'!I18 -> -8104 | F18: =F15 -> 0 | G18: =F18+E18 -> -8104 | H18: =C30 -> 0 | I18: =G18-H18 -> -8104
E20: Credit
E21: Name | F21: Opening | G21: Today | H21: Receive | I21: Balance
F22: ='21'!I22 -> 20126 | I22: =F22+G22-H22 -> 20126
F23: ='21'!I23 -> 410 | I23: =F23+G23-H23 -> 410
F24: ='21'!I24 -> 0 | I24: =F24+G24-H24 -> 0
F25: ='21'!I25 -> 8300 | I25: =F25+G25-H25 -> 8300
F26: ='21'!I26 -> 10000 | I26: =F26+G26-H26 -> 10000
F27: ='21'!I27 -> 20000 | I27: =F27+G27-H27 -> 20000
F28: ='21'!I28 -> 1000 | I28: =F28+G28-H28 -> 1000
F29: ='21'!I29 -> 1000 | I29: =F29+G29-H29 -> 1000
A30: TOTAL | C30: =SUM(C3:C29) -> 0 | F30: ='21'!I30 -> 5000 | I30: =F30+G30-H30 -> 5000
F31: ='21'!I31 -> 0 | I31: =F31+G31-H31 -> 0
F32: ='21'!I32 -> 0 | I32: =F32+G32-H32 -> 0
F33: ='21'!I33 -> 0 | I33: =F33+G33-H33 -> 0
F34: ='21'!I34 -> 0 | I34: =F34+G34-H34 -> 0
F35: ='21'!I35 -> 0 | I35: =F35+G35-H35 -> 0
F36: ='21'!I36 -> 0 | I36: =F36+G36-H36 -> 0
F37: ='21'!I37 -> 0 | I37: =F37+G37-H37 -> 0
F38: ='21'!I38 -> 0 | I38: =F38+G38-H38 -> 0
F39: ='21'!I39 -> 0 | I39: =F39+G39-H39 -> 0
F40: ='21'!I40 -> 0 | I40: =F40+G40-H40 -> 0
E41: Total | F41: =SUM(F22:F40) -> 65836 | G41: =SUM(G22:G40) -> 0 | H41: =SUM(H22:H40) -> 0 | I41: =F41+G41-H41 -> 65836

Sheet 23
A1: EXPENSES
A2: Name | B2: Description | C2: Amount | E2: Commissions | H2: Franchise Owner
E3: Jazz Load | H3: Opening Bal | I3: ='22'!I15 -> 102056
E4: Jazz Cash | K4: Date | L4: Jazz Load | M4: Jazz Cash | N4: Efics MFS | O4: Efics Bill | P4: SIM Commission | Q4: Retail IMSI | R4: Franchise IMSI | S4: GST Comm | T4: Tax Rebate | U4: MNP | V4: Other | W4: Other | X4: TOTAL
E5: Efics MFS | K5: 23 | L5: =F3 -> 0 | M5: =F4 -> 0 | N5: =F5 -> 0 | O5: =F6 -> 0 | P5: =F7 -> 0 | Q5: =F8 -> 0 | R5: =F9 -> 0 | S5: =F10 -> 0 | T5: =F11 -> 0 | U5: =F12 -> 0 | V5: =F13 -> 0 | W5: =F14 -> 0 | X5: =SUM(L5:W5) -> 0
E6: Efics BILL
E7: SIM Commission
E8: Retail IMSI
E9: Franchise IMSI
E10: GST Comm
E11: Tax Claim Rebate
E12: MNP Comm
E13: Other
E14: Other
E15: Total | F15: =SUM(F3:F14) -> 0 | H15: Total | I15: =SUM(I3:I14) -> 102056
E17: Opening Bal | F17: Issue Balance | G17: Total | H17: Expense | I17: Return
E18: ='22'!I18 -> -8104 | F18: =F15 -> 0 | G18: =F18+E18 -> -8104 | H18: =C30 -> 0 | I18: =G18-H18 -> -8104
E20: Credit
E21: Name | F21: Opening | G21: Today | H21: Receive | I21: Balance
F22: ='22'!I22 -> 20126 | I22: =F22+G22-H22 -> 20126
F23: ='22'!I23 -> 410 | I23: =F23+G23-H23 -> 410
F24: ='22'!I24 -> 0 | I24: =F24+G24-H24 -> 0
F25: ='22'!I25 -> 8300 | I25: =F25+G25-H25 -> 8300
F26: ='22'!I26 -> 10000 | I26: =F26+G26-H26 -> 10000
F27: ='22'!I27 -> 20000 | I27: =F27+G27-H27 -> 20000
F28: ='22'!I28 -> 1000 | I28: =F28+G28-H28 -> 1000
F29: ='22'!I29 -> 1000 | I29: =F29+G29-H29 -> 1000
A30: TOTAL | C30: =SUM(C3:C29) -> 0 | F30: ='22'!I30 -> 5000 | I30: =F30+G30-H30 -> 5000
F31: ='22'!I31 -> 0 | I31: =F31+G31-H31 -> 0
F32: ='22'!I32 -> 0 | I32: =F32+G32-H32 -> 0
F33: ='22'!I33 -> 0 | I33: =F33+G33-H33 -> 0
F34: ='22'!I34 -> 0 | I34: =F34+G34-H34 -> 0
F35: ='22'!I35 -> 0 | I35: =F35+G35-H35 -> 0
F36: ='22'!I36 -> 0 | I36: =F36+G36-H36 -> 0
F37: ='22'!I37 -> 0 | I37: =F37+G37-H37 -> 0
F38: ='22'!I38 -> 0 | I38: =F38+G38-H38 -> 0
F39: ='22'!I39 -> 0 | I39: =F39+G39-H39 -> 0
F40: ='22'!I40 -> 0 | I40: =F40+G40-H40 -> 0
E41: Total | F41: =SUM(F22:F40) -> 65836 | G41: =SUM(G22:G40) -> 0 | H41: =SUM(H22:H40) -> 0 | I41: =F41+G41-H41 -> 65836

Sheet 24
A1: EXPENSES
A2: Name | B2: Description | C2: Amount | E2: Commissions | H2: Franchise Owner
E3: Jazz Load | H3: Opening Bal | I3: ='23'!I15 -> 102056
E4: Jazz Cash | K4: Date | L4: Jazz Load | M4: Jazz Cash | N4: Efics MFS | O4: Efics Bill | P4: SIM Commission | Q4: Retail IMSI | R4: Franchise IMSI | S4: GST Comm | T4: Tax Rebate | U4: MNP | V4: Other | W4: Other | X4: TOTAL
E5: Efics MFS | K5: 24 | L5: =F3 -> 0 | M5: =F4 -> 0 | N5: =F5 -> 0 | O5: =F6 -> 0 | P5: =F7 -> 0 | Q5: =F8 -> 0 | R5: =F9 -> 0 | S5: =F10 -> 0 | T5: =F11 -> 0 | U5: =F12 -> 0 | V5: =F13 -> 0 | W5: =F14 -> 0 | X5: =SUM(L5:W5) -> 0
E6: Efics BILL
E7: SIM Commission
E8: Retail IMSI
E9: Franchise IMSI
E10: GST Comm
E11: Tax Claim Rebate
E12: MNP Comm
E13: Other
E14: Other
E15: Total | F15: =SUM(F3:F14) -> 0 | H15: Total | I15: =SUM(I3:I14) -> 102056
E17: Opening Bal | F17: Issue Balance | G17: Total | H17: Expense | I17: Return
E18: ='23'!I18 -> -8104 | F18: =F15 -> 0 | G18: =F18+E18 -> -8104 | H18: =C30 -> 0 | I18: =G18-H18 -> -8104
E20: Credit
E21: Name | F21: Opening | G21: Today | H21: Receive | I21: Balance
F22: ='23'!I22 -> 20126 | I22: =F22+G22-H22 -> 20126
F23: ='23'!I23 -> 410 | I23: =F23+G23-H23 -> 410
F24: ='23'!I24 -> 0 | I24: =F24+G24-H24 -> 0
F25: ='23'!I25 -> 8300 | I25: =F25+G25-H25 -> 8300
F26: ='23'!I26 -> 10000 | I26: =F26+G26-H26 -> 10000
F27: ='23'!I27 -> 20000 | I27: =F27+G27-H27 -> 20000
F28: ='23'!I28 -> 1000 | I28: =F28+G28-H28 -> 1000
F29: ='23'!I29 -> 1000 | I29: =F29+G29-H29 -> 1000
A30: TOTAL | C30: =SUM(C3:C29) -> 0 | F30: ='23'!I30 -> 5000 | I30: =F30+G30-H30 -> 5000
F31: ='23'!I31 -> 0 | I31: =F31+G31-H31 -> 0
F32: ='23'!I32 -> 0 | I32: =F32+G32-H32 -> 0
F33: ='23'!I33 -> 0 | I33: =F33+G33-H33 -> 0
F34: ='23'!I34 -> 0 | I34: =F34+G34-H34 -> 0
F35: ='23'!I35 -> 0 | I35: =F35+G35-H35 -> 0
F36: ='23'!I36 -> 0 | I36: =F36+G36-H36 -> 0
F37: ='23'!I37 -> 0 | I37: =F37+G37-H37 -> 0
F38: ='23'!I38 -> 0 | I38: =F38+G38-H38 -> 0
F39: ='23'!I39 -> 0 | I39: =F39+G39-H39 -> 0
F40: ='23'!I40 -> 0 | I40: =F40+G40-H40 -> 0
E41: Total | F41: =SUM(F22:F40) -> 65836 | G41: =SUM(G22:G40) -> 0 | H41: =SUM(H22:H40) -> 0 | I41: =F41+G41-H41 -> 65836

Sheet 25
A1: EXPENSES
A2: Name | B2: Description | C2: Amount | E2: Commissions | H2: Franchise Owner
E3: Jazz Load | H3: Opening Bal | I3: ='24'!I15 -> 102056
E4: Jazz Cash | K4: Date | L4: Jazz Load | M4: Jazz Cash | N4: Efics MFS | O4: Efics Bill | P4: SIM Commission | Q4: Retail IMSI | R4: Franchise IMSI | S4: GST Comm | T4: Tax Rebate | U4: MNP | V4: Other | W4: Other | X4: TOTAL
E5: Efics MFS | K5: 25 | L5: =F3 -> 0 | M5: =F4 -> 0 | N5: =F5 -> 0 | O5: =F6 -> 0 | P5: =F7 -> 0 | Q5: =F8 -> 0 | R5: =F9 -> 0 | S5: =F10 -> 0 | T5: =F11 -> 0 | U5: =F12 -> 0 | V5: =F13 -> 0 | W5: =F14 -> 0 | X5: =SUM(L5:W5) -> 0
E6: Efics BILL
E7: SIM Commission
E8: Retail IMSI
E9: Franchise IMSI
E10: GST Comm
E11: Tax Claim Rebate
E12: MNP Comm
E13: Other
E14: Other
E15: Total | F15: =SUM(F3:F14) -> 0 | H15: Total | I15: =SUM(I3:I14) -> 102056
E17: Opening Bal | F17: Issue Balance | G17: Total | H17: Expense | I17: Return
E18: ='24'!I18 -> -8104 | F18: =F15 -> 0 | G18: =F18+E18 -> -8104 | H18: =C30 -> 0 | I18: =G18-H18 -> -8104
E20: Credit
E21: Name | F21: Opening | G21: Today | H21: Receive | I21: Balance
F22: ='24'!I22 -> 20126 | I22: =F22+G22-H22 -> 20126
F23: ='24'!I23 -> 410 | I23: =F23+G23-H23 -> 410
F24: ='24'!I24 -> 0 | I24: =F24+G24-H24 -> 0
F25: ='24'!I25 -> 8300 | I25: =F25+G25-H25 -> 8300
F26: ='24'!I26 -> 10000 | I26: =F26+G26-H26 -> 10000
F27: ='24'!I27 -> 20000 | I27: =F27+G27-H27 -> 20000
F28: ='24'!I28 -> 1000 | I28: =F28+G28-H28 -> 1000
F29: ='24'!I29 -> 1000 | I29: =F29+G29-H29 -> 1000
A30: TOTAL | C30: =SUM(C3:C29) -> 0 | F30: ='24'!I30 -> 5000 | I30: =F30+G30-H30 -> 5000
F31: ='24'!I31 -> 0 | I31: =F31+G31-H31 -> 0
F32: ='24'!I32 -> 0 | I32: =F32+G32-H32 -> 0
F33: ='24'!I33 -> 0 | I33: =F33+G33-H33 -> 0
F34: ='24'!I34 -> 0 | I34: =F34+G34-H34 -> 0
F35: ='24'!I35 -> 0 | I35: =F35+G35-H35 -> 0
F36: ='24'!I36 -> 0 | I36: =F36+G36-H36 -> 0
F37: ='24'!I37 -> 0 | I37: =F37+G37-H37 -> 0
F38: ='24'!I38 -> 0 | I38: =F38+G38-H38 -> 0
F39: ='24'!I39 -> 0 | I39: =F39+G39-H39 -> 0
F40: ='24'!I40 -> 0 | I40: =F40+G40-H40 -> 0
E41: Total | F41: =SUM(F22:F40) -> 65836 | G41: =SUM(G22:G40) -> 0 | H41: =SUM(H22:H40) -> 0 | I41: =F41+G41-H41 -> 65836

Sheet 26
A1: EXPENSES
A2: Name | B2: Description | C2: Amount | E2: Commissions | H2: Franchise Owner
E3: Jazz Load | H3: Opening Bal | I3: ='25'!I15 -> 102056
E4: Jazz Cash | K4: Date | L4: Jazz Load | M4: Jazz Cash | N4: Efics MFS | O4: Efics Bill | P4: SIM Commission | Q4: Retail IMSI | R4: Franchise IMSI | S4: GST Comm | T4: Tax Rebate | U4: MNP | V4: Other | W4: Other | X4: TOTAL
E5: Efics MFS | K5: 26 | L5: =F3 -> 0 | M5: =F4 -> 0 | N5: =F5 -> 0 | O5: =F6 -> 0 | P5: =F7 -> 0 | Q5: =F8 -> 0 | R5: =F9 -> 0 | S5: =F10 -> 0 | T5: =F11 -> 0 | U5: =F12 -> 0 | V5: =F13 -> 0 | W5: =F14 -> 0 | X5: =SUM(L5:W5) -> 0
E6: Efics BILL
E7: SIM Commission
E8: Retail IMSI
E9: Franchise IMSI
E10: GST Comm
E11: Tax Claim Rebate
E12: MNP Comm
E13: Other
E14: Other
E15: Total | F15: =SUM(F3:F14) -> 0 | H15: Total | I15: =SUM(I3:I14) -> 102056
E17: Opening Bal | F17: Issue Balance | G17: Total | H17: Expense | I17: Return
E18: ='25'!I18 -> -8104 | F18: =F15 -> 0 | G18: =F18+E18 -> -8104 | H18: =C30 -> 0 | I18: =G18-H18 -> -8104
E20: Credit
E21: Name | F21: Opening | G21: Today | H21: Receive | I21: Balance
F22: ='25'!I22 -> 20126 | I22: =F22+G22-H22 -> 20126
F23: ='25'!I23 -> 410 | I23: =F23+G23-H23 -> 410
F24: ='25'!I24 -> 0 | I24: =F24+G24-H24 -> 0
F25: ='25'!I25 -> 8300 | I25: =F25+G25-H25 -> 8300
F26: ='25'!I26 -> 10000 | I26: =F26+G26-H26 -> 10000
F27: ='25'!I27 -> 20000 | I27: =F27+G27-H27 -> 20000
F28: ='25'!I28 -> 1000 | I28: =F28+G28-H28 -> 1000
F29: ='25'!I29 -> 1000 | I29: =F29+G29-H29 -> 1000
A30: TOTAL | C30: =SUM(C3:C29) -> 0 | F30: ='25'!I30 -> 5000 | I30: =F30+G30-H30 -> 5000
F31: ='25'!I31 -> 0 | I31: =F31+G31-H31 -> 0
F32: ='25'!I32 -> 0 | I32: =F32+G32-H32 -> 0
F33: ='25'!I33 -> 0 | I33: =F33+G33-H33 -> 0
F34: ='25'!I34 -> 0 | I34: =F34+G34-H34 -> 0
F35: ='25'!I35 -> 0 | I35: =F35+G35-H35 -> 0
F36: ='25'!I36 -> 0 | I36: =F36+G36-H36 -> 0
F37: ='25'!I37 -> 0 | I37: =F37+G37-H37 -> 0
F38: ='25'!I38 -> 0 | I38: =F38+G38-H38 -> 0
F39: ='25'!I39 -> 0 | I39: =F39+G39-H39 -> 0
F40: ='25'!I40 -> 0 | I40: =F40+G40-H40 -> 0
E41: Total | F41: =SUM(F22:F40) -> 65836 | G41: =SUM(G22:G40) -> 0 | H41: =SUM(H22:H40) -> 0 | I41: =F41+G41-H41 -> 65836

Sheet 27
A1: EXPENSES
A2: Name | B2: Description | C2: Amount | E2: Commissions | H2: Franchise Owner
E3: Jazz Load | H3: Opening Bal | I3: ='26'!I15 -> 102056
E4: Jazz Cash | K4: Date | L4: Jazz Load | M4: Jazz Cash | N4: Efics MFS | O4: Efics Bill | P4: SIM Commission | Q4: Retail IMSI | R4: Franchise IMSI | S4: GST Comm | T4: Tax Rebate | U4: MNP | V4: Other | W4: Other | X4: TOTAL
E5: Efics MFS | K5: 27 | L5: =F3 -> 0 | M5: =F4 -> 0 | N5: =F5 -> 0 | O5: =F6 -> 0 | P5: =F7 -> 0 | Q5: =F8 -> 0 | R5: =F9 -> 0 | S5: =F10 -> 0 | T5: =F11 -> 0 | U5: =F12 -> 0 | V5: =F13 -> 0 | W5: =F14 -> 0 | X5: =SUM(L5:W5) -> 0
E6: Efics BILL
E7: SIM Commission
E8: Retail IMSI
E9: Franchise IMSI
E10: GST Comm
E11: Tax Claim Rebate
E12: MNP Comm
E13: Other
E14: Other
E15: Total | F15: =SUM(F3:F14) -> 0 | H15: Total | I15: =SUM(I3:I14) -> 102056
E17: Opening Bal | F17: Issue Balance | G17: Total | H17: Expense | I17: Return
E18: ='26'!I18 -> -8104 | F18: =F15 -> 0 | G18: =F18+E18 -> -8104 | H18: =C30 -> 0 | I18: =G18-H18 -> -8104
E20: Credit
E21: Name | F21: Opening | G21: Today | H21: Receive | I21: Balance
F22: ='26'!I22 -> 20126 | I22: =F22+G22-H22 -> 20126
F23: ='26'!I23 -> 410 | I23: =F23+G23-H23 -> 410
F24: ='26'!I24 -> 0 | I24: =F24+G24-H24 -> 0
F25: ='26'!I25 -> 8300 | I25: =F25+G25-H25 -> 8300
F26: ='26'!I26 -> 10000 | I26: =F26+G26-H26 -> 10000
F27: ='26'!I27 -> 20000 | I27: =F27+G27-H27 -> 20000
F28: ='26'!I28 -> 1000 | I28: =F28+G28-H28 -> 1000
F29: ='26'!I29 -> 1000 | I29: =F29+G29-H29 -> 1000
A30: TOTAL | C30: =SUM(C3:C29) -> 0 | F30: ='26'!I30 -> 5000 | I30: =F30+G30-H30 -> 5000
F31: ='26'!I31 -> 0 | I31: =F31+G31-H31 -> 0
F32: ='26'!I32 -> 0 | I32: =F32+G32-H32 -> 0
F33: ='26'!I33 -> 0 | I33: =F33+G33-H33 -> 0
F34: ='26'!I34 -> 0 | I34: =F34+G34-H34 -> 0
F35: ='26'!I35 -> 0 | I35: =F35+G35-H35 -> 0
F36: ='26'!I36 -> 0 | I36: =F36+G36-H36 -> 0
F37: ='26'!I37 -> 0 | I37: =F37+G37-H37 -> 0
F38: ='26'!I38 -> 0 | I38: =F38+G38-H38 -> 0
F39: ='26'!I39 -> 0 | I39: =F39+G39-H39 -> 0
F40: ='26'!I40 -> 0 | I40: =F40+G40-H40 -> 0
E41: Total | F41: =SUM(F22:F40) -> 65836 | G41: =SUM(G22:G40) -> 0 | H41: =SUM(H22:H40) -> 0 | I41: =F41+G41-H41 -> 65836

Sheet 28
A1: EXPENSES
A2: Name | B2: Description | C2: Amount | E2: Commissions | H2: Franchise Owner
E3: Jazz Load | H3: Opening Bal | I3: ='27'!I15 -> 102056
E4: Jazz Cash | K4: Date | L4: Jazz Load | M4: Jazz Cash | N4: Efics MFS | O4: Efics Bill | P4: SIM Commission | Q4: Retail IMSI | R4: Franchise IMSI | S4: GST Comm | T4: Tax Rebate | U4: MNP | V4: Other | W4: Other | X4: TOTAL
E5: Efics MFS | K5: 28 | L5: =F3 -> 0 | M5: =F4 -> 0 | N5: =F5 -> 0 | O5: =F6 -> 0 | P5: =F7 -> 0 | Q5: =F8 -> 0 | R5: =F9 -> 0 | S5: =F10 -> 0 | T5: =F11 -> 0 | U5: =F12 -> 0 | V5: =F13 -> 0 | W5: =F14 -> 0 | X5: =SUM(L5:W5) -> 0
E6: Efics BILL
E7: SIM Commission
E8: Retail IMSI
E9: Franchise IMSI
E10: GST Comm
E11: Tax Claim Rebate
E12: MNP Comm
E13: Other
E14: Other
E15: Total | F15: =SUM(F3:F14) -> 0 | H15: Total | I15: =SUM(I3:I14) -> 102056
E17: Opening Bal | F17: Issue Balance | G17: Total | H17: Expense | I17: Return
E18: ='27'!I18 -> -8104 | F18: =F15 -> 0 | G18: =F18+E18 -> -8104 | H18: =C30 -> 0 | I18: =G18-H18 -> -8104
E20: Credit
E21: Name | F21: Opening | G21: Today | H21: Receive | I21: Balance
F22: ='27'!I22 -> 20126 | I22: =F22+G22-H22 -> 20126
F23: ='27'!I23 -> 410 | I23: =F23+G23-H23 -> 410
F24: ='27'!I24 -> 0 | I24: =F24+G24-H24 -> 0
F25: ='27'!I25 -> 8300 | I25: =F25+G25-H25 -> 8300
F26: ='27'!I26 -> 10000 | I26: =F26+G26-H26 -> 10000
F27: ='27'!I27 -> 20000 | I27: =F27+G27-H27 -> 20000
F28: ='27'!I28 -> 1000 | I28: =F28+G28-H28 -> 1000
F29: ='27'!I29 -> 1000 | I29: =F29+G29-H29 -> 1000
A30: TOTAL | C30: =SUM(C3:C29) -> 0 | F30: ='27'!I30 -> 5000 | I30: =F30+G30-H30 -> 5000
F31: ='27'!I31 -> 0 | I31: =F31+G31-H31 -> 0
F32: ='27'!I32 -> 0 | I32: =F32+G32-H32 -> 0
F33: ='27'!I33 -> 0 | I33: =F33+G33-H33 -> 0
F34: ='27'!I34 -> 0 | I34: =F34+G34-H34 -> 0
F35: ='27'!I35 -> 0 | I35: =F35+G35-H35 -> 0
F36: ='27'!I36 -> 0 | I36: =F36+G36-H36 -> 0
F37: ='27'!I37 -> 0 | I37: =F37+G37-H37 -> 0
F38: ='27'!I38 -> 0 | I38: =F38+G38-H38 -> 0
F39: ='27'!I39 -> 0 | I39: =F39+G39-H39 -> 0
F40: ='27'!I40 -> 0 | I40: =F40+G40-H40 -> 0
E41: Total | F41: =SUM(F22:F40) -> 65836 | G41: =SUM(G22:G40) -> 0 | H41: =SUM(H22:H40) -> 0 | I41: =F41+G41-H41 -> 65836

Sheet 29
A1: EXPENSES
A2: Name | B2: Description | C2: Amount | E2: Commissions | H2: Franchise Owner
E3: Jazz Load | H3: Opening Bal | I3: ='28'!I15 -> 102056
E4: Jazz Cash | K4: Date | L4: Jazz Load | M4: Jazz Cash | N4: Efics MFS | O4: Efics Bill | P4: SIM Commission | Q4: Retail IMSI | R4: Franchise IMSI | S4: GST Comm | T4: Tax Rebate | U4: MNP | V4: Other | W4: Other | X4: TOTAL
E5: Efics MFS | K5: 29 | L5: =F3 -> 0 | M5: =F4 -> 0 | N5: =F5 -> 0 | O5: =F6 -> 0 | P5: =F7 -> 0 | Q5: =F8 -> 0 | R5: =F9 -> 0 | S5: =F10 -> 0 | T5: =F11 -> 0 | U5: =F12 -> 0 | V5: =F13 -> 0 | W5: =F14 -> 0 | X5: =SUM(L5:W5) -> 0
E6: Efics BILL
E7: SIM Commission
E8: Retail IMSI
E9: Franchise IMSI
E10: GST Comm
E11: Tax Claim Rebate
E12: MNP Comm
E13: Other
E14: Other
E15: Total | F15: =SUM(F3:F14) -> 0 | H15: Total | I15: =SUM(I3:I14) -> 102056
E17: Opening Bal | F17: Issue Balance | G17: Total | H17: Expense | I17: Return
E18: ='28'!I18 -> -8104 | F18: =F15 -> 0 | G18: =F18+E18 -> -8104 | H18: =C30 -> 0 | I18: =G18-H18 -> -8104
E20: Credit
E21: Name | F21: Opening | G21: Today | H21: Receive | I21: Balance
F22: ='28'!I22 -> 20126 | I22: =F22+G22-H22 -> 20126
F23: ='28'!I23 -> 410 | I23: =F23+G23-H23 -> 410
F24: ='28'!I24 -> 0 | I24: =F24+G24-H24 -> 0
F25: ='28'!I25 -> 8300 | I25: =F25+G25-H25 -> 8300
F26: ='28'!I26 -> 10000 | I26: =F26+G26-H26 -> 10000
F27: ='28'!I27 -> 20000 | I27: =F27+G27-H27 -> 20000
F28: ='28'!I28 -> 1000 | I28: =F28+G28-H28 -> 1000
F29: ='28'!I29 -> 1000 | I29: =F29+G29-H29 -> 1000
A30: TOTAL | C30: =SUM(C3:C29) -> 0 | F30: ='28'!I30 -> 5000 | I30: =F30+G30-H30 -> 5000
F31: ='28'!I31 -> 0 | I31: =F31+G31-H31 -> 0
F32: ='28'!I32 -> 0 | I32: =F32+G32-H32 -> 0
F33: ='28'!I33 -> 0 | I33: =F33+G33-H33 -> 0
F34: ='28'!I34 -> 0 | I34: =F34+G34-H34 -> 0
F35: ='28'!I35 -> 0 | I35: =F35+G35-H35 -> 0
F36: ='28'!I36 -> 0 | I36: =F36+G36-H36 -> 0
F37: ='28'!I37 -> 0 | I37: =F37+G37-H37 -> 0
F38: ='28'!I38 -> 0 | I38: =F38+G38-H38 -> 0
F39: ='28'!I39 -> 0 | I39: =F39+G39-H39 -> 0
F40: ='28'!I40 -> 0 | I40: =F40+G40-H40 -> 0
E41: Total | F41: =SUM(F22:F40) -> 65836 | G41: =SUM(G22:G40) -> 0 | H41: =SUM(H22:H40) -> 0 | I41: =F41+G41-H41 -> 65836

Sheet 30
A1: EXPENSES
A2: Name | B2: Description | C2: Amount | E2: Commissions | H2: Franchise Owner
E3: Jazz Load | H3: Opening Bal | I3: ='29'!I15 -> 102056
E4: Jazz Cash | K4: Date | L4: Jazz Load | M4: Jazz Cash | N4: Efics MFS | O4: Efics Bill | P4: SIM Commission | Q4: Retail IMSI | R4: Franchise IMSI | S4: GST Comm | T4: Tax Rebate | U4: MNP | V4: Other | W4: Other | X4: TOTAL
E5: Efics MFS | K5: 30 | L5: =F3 -> 0 | M5: =F4 -> 0 | N5: =F5 -> 0 | O5: =F6 -> 0 | P5: =F7 -> 0 | Q5: =F8 -> 0 | R5: =F9 -> 0 | S5: =F10 -> 0 | T5: =F11 -> 0 | U5: =F12 -> 0 | V5: =F13 -> 0 | W5: =F14 -> 0 | X5: =SUM(L5:W5) -> 0
E6: Efics BILL
E7: SIM Commission
E8: Retail IMSI
E9: Franchise IMSI
E10: GST Comm
E11: Tax Claim Rebate
E12: MNP Comm
E13: Other
E14: Other
E15: Total | F15: =SUM(F3:F14) -> 0 | H15: Total | I15: =SUM(I3:I14) -> 102056
E17: Opening Bal | F17: Issue Balance | G17: Total | H17: Expense | I17: Return
E18: ='29'!I18 -> -8104 | F18: =F15 -> 0 | G18: =F18+E18 -> -8104 | H18: =C30 -> 0 | I18: =G18-H18 -> -8104
E20: Credit
E21: Name | F21: Opening | G21: Today | H21: Receive | I21: Balance
F22: ='29'!I22 -> 20126 | I22: =F22+G22-H22 -> 20126
F23: ='29'!I23 -> 410 | I23: =F23+G23-H23 -> 410
F24: ='29'!I24 -> 0 | I24: =F24+G24-H24 -> 0
F25: ='29'!I25 -> 8300 | I25: =F25+G25-H25 -> 8300
F26: ='29'!I26 -> 10000 | I26: =F26+G26-H26 -> 10000
F27: ='29'!I27 -> 20000 | I27: =F27+G27-H27 -> 20000
F28: ='29'!I28 -> 1000 | I28: =F28+G28-H28 -> 1000
F29: ='29'!I29 -> 1000 | I29: =F29+G29-H29 -> 1000
A30: TOTAL | C30: =SUM(C3:C29) -> 0 | F30: ='29'!I30 -> 5000 | I30: =F30+G30-H30 -> 5000
F31: ='29'!I31 -> 0 | I31: =F31+G31-H31 -> 0
F32: ='29'!I32 -> 0 | I32: =F32+G32-H32 -> 0
F33: ='29'!I33 -> 0 | I33: =F33+G33-H33 -> 0
F34: ='29'!I34 -> 0 | I34: =F34+G34-H34 -> 0
F35: ='29'!I35 -> 0 | I35: =F35+G35-H35 -> 0
F36: ='29'!I36 -> 0 | I36: =F36+G36-H36 -> 0
F37: ='29'!I37 -> 0 | I37: =F37+G37-H37 -> 0
F38: ='29'!I38 -> 0 | I38: =F38+G38-H38 -> 0
F39: ='29'!I39 -> 0 | I39: =F39+G39-H39 -> 0
F40: ='29'!I40 -> 0 | I40: =F40+G40-H40 -> 0
E41: Total | F41: =SUM(F22:F40) -> 65836 | G41: =SUM(G22:G40) -> 0 | H41: =SUM(H22:H40) -> 0 | I41: =F41+G41-H41 -> 65836

Sheet 31
A1: EXPENSES
A2: Name | B2: Description | C2: Amount | E2: Commissions | H2: Franchise Owner
E3: Jazz Load | H3: Opening Bal | I3: ='30'!I15 -> 102056
E4: Jazz Cash | K4: Date | L4: Jazz Load | M4: Jazz Cash | N4: Efics MFS | O4: Efics Bill | P4: SIM Commission | Q4: Retail IMSI | R4: Franchise IMSI | S4: GST Comm | T4: Tax Rebate | U4: MNP | V4: Other | W4: Other | X4: TOTAL
E5: Efics MFS | K5: 31 | L5: =F3 -> 0 | M5: =F4 -> 0 | N5: =F5 -> 0 | O5: =F6 -> 0 | P5: =F7 -> 0 | Q5: =F8 -> 0 | R5: =F9 -> 0 | S5: =F10 -> 0 | T5: =F11 -> 0 | U5: =F12 -> 0 | V5: =F13 -> 0 | W5: =F14 -> 0 | X5: =SUM(L5:W5) -> 0
E6: Efics BILL
E7: SIM Commission
E8: Retail IMSI
E9: Franchise IMSI
E10: GST Comm
E11: Tax Claim Rebate
E12: MNP Comm
E13: Other
E14: Other
E15: Total | F15: =SUM(F3:F14) -> 0 | H15: Total | I15: =SUM(I3:I14) -> 102056
E17: Opening Bal | F17: Issue Balance | G17: Total | H17: Expense | I17: Return
E18: ='30'!I18 -> -8104 | F18: =F15 -> 0 | G18: =F18+E18 -> -8104 | H18: =C30 -> 0 | I18: =G18-H18 -> -8104
E20: Credit
E21: Name | F21: Opening | G21: Today | H21: Receive | I21: Balance
F22: ='30'!I22 -> 20126 | I22: =F22+G22-H22 -> 20126
F23: ='30'!I23 -> 410 | I23: =F23+G23-H23 -> 410
F24: ='30'!I24 -> 0 | I24: =F24+G24-H24 -> 0
F25: ='30'!I25 -> 8300 | I25: =F25+G25-H25 -> 8300
F26: ='30'!I26 -> 10000 | I26: =F26+G26-H26 -> 10000
F27: ='30'!I27 -> 20000 | I27: =F27+G27-H27 -> 20000
F28: ='30'!I28 -> 1000 | I28: =F28+G28-H28 -> 1000
F29: ='30'!I29 -> 1000 | I29: =F29+G29-H29 -> 1000
A30: TOTAL | C30: =SUM(C3:C29) -> 0 | F30: ='30'!I30 -> 5000 | I30: =F30+G30-H30 -> 5000
F31: ='30'!I31 -> 0 | I31: =F31+G31-H31 -> 0
F32: ='30'!I32 -> 0 | I32: =F32+G32-H32 -> 0
F33: ='30'!I33 -> 0 | I33: =F33+G33-H33 -> 0
F34: ='30'!I34 -> 0 | I34: =F34+G34-H34 -> 0
F35: ='30'!I35 -> 0 | I35: =F35+G35-H35 -> 0
F36: ='30'!I36 -> 0 | I36: =F36+G36-H36 -> 0
F37: ='30'!I37 -> 0 | I37: =F37+G37-H37 -> 0
F38: ='30'!I38 -> 0 | I38: =F38+G38-H38 -> 0
F39: ='30'!I39 -> 0 | I39: =F39+G39-H39 -> 0
F40: ='30'!I40 -> 0 | I40: =F40+G40-H40 -> 0
E41: Total | F41: =SUM(F22:F40) -> 65836 | G41: =SUM(G22:G40) -> 0 | H41: =SUM(H22:H40) -> 0 | I41: =F41+G41-H41 -> 65836

Sheet FINAL
A1: EXPENSES
A2: Name | B2: Description | C2: Amount | E2: Commissions | H2: Franchise Owner
B3: POSPAID IMSI February ( 20*390 | C3: 7800 | E3: Jazz Load | F3: 14806 | H3: Opening Bal | I3: ='30'!I15 -> 102056
E4: Jazz Cash | K4: Date | L4: Jazz Load | M4: Jazz Cash | N4: Efics MFS | O4: Efics Bill | P4: SIM Commission | Q4: Retail IMSI | R4: Franchise IMSI | S4: GST Comm | T4: Tax Rebate | U4: MNP | V4: Other | W4: Other | X4: TOTAL
E5: Efics MFS | K5: 31 | L5: =F3 -> 14806 | M5: =F4 -> 0 | N5: =F5 -> 0 | O5: =F6 -> 0 | P5: =F7 -> 0 | Q5: =F8 -> 0 | R5: =F9 -> 0 | S5: =F10 -> 0 | T5: =F11 -> 0 | U5: =F12 -> 0 | V5: =F13 -> 0 | W5: =F14 -> 0 | X5: =SUM(L5:W5) -> 14806
E6: Efics BILL
E7: SIM Commission
E8: Retail IMSI
E9: Franchise IMSI
E10: GST Comm
E11: Tax Claim Rebate
E12: MNP Comm
E13: Other
E14: Other
E15: Total | F15: =SUM(F3:F14) -> 14806 | H15: Total | I15: =SUM(I3:I14) -> 102056
E17: Opening Bal | F17: Issue Balance | G17: Total | H17: Expense | I17: Return
E18: ='31'!I18 -> -8104 | F18: =F15 -> 14806 | G18: =F18+E18 -> 6702 | H18: =C30 -> 7800 | I18: =G18-H18 -> -1098
E20: Credit
E21: Name | F21: Opening | G21: Today | H21: Receive | I21: Balance
E22: ALI OLAKH | F22: ='30'!I22 -> 20126 | I22: =F22+G22-H22 -> 20126
E23: Usman cheema | F23: ='30'!I23 -> 410 | I23: =F23+G23-H23 -> 410
E24: ZEESHAN OFFICES | F24: ='30'!I24 -> 0 | I24: =F24+G24-H24 -> 0
E25: IMRAN OLAKH | F25: ='30'!I25 -> 8300 | I25: =F25+G25-H25 -> 8300
E26: NAVEED DO | F26: ='30'!I26 -> 10000 | I26: =F26+G26-H26 -> 10000
E27: SEHAR CCR | F27: ='30'!I27 -> 20000 | I27: =F27+G27-H27 -> 20000
E28: Qurat ul Anny | F28: ='30'!I28 -> 1000 | I28: =F28+G28-H28 -> 1000
E29: SARAM CCR | F29: ='30'!I29 -> 1000 | I29: =F29+G29-H29 -> 1000
A30: TOTAL | C30: =SUM(C3:C29) -> 7800 | E30: TATAS CCR | F30: ='30'!I30 -> 5000 | I30: =F30+G30-H30 -> 5000
E31: AKHTAR | F31: ='30'!I31 -> 0 | I31: =F31+G31-H31 -> 0
E32: ARSLAN DO | F32: ='30'!I32 -> 0 | I32: =F32+G32-H32 -> 0
F33: ='30'!I33 -> 0 | I33: =F33+G33-H33 -> 0
F34: ='30'!I34 -> 0 | I34: =F34+G34-H34 -> 0
F35: ='30'!I35 -> 0 | I35: =F35+G35-H35 -> 0
F36: ='30'!I36 -> 0 | I36: =F36+G36-H36 -> 0
F37: ='30'!I37 -> 0 | I37: =F37+G37-H37 -> 0
F38: ='30'!I38 -> 0 | I38: =F38+G38-H38 -> 0
F39: ='30'!I39 -> 0 | I39: =F39+G39-H39 -> 0
F40: ='30'!I40 -> 0 | I40: =F40+G40-H40 -> 0
E41: Total | F41: =SUM(F22:F40) -> 65836 | G41: =SUM(G22:G40) -> 0 | H41: =SUM(H22:H40) -> 0 | I41: =F41+G41-H41 -> 65836
